[
  {
    "id": "1930297242050801865",
    "accountId": "whyyoutouzhele",
    "sensitive": false,
    "name": "李老师不是你老师",
    "createdDate": "2025-06-05 00:15:00",
    "content": "6月4日，打拐志愿者上官正义举报并端掉了在湖南岳阳岳阳临湘聂士镇镇辖区的黑砖厂，他们利用残障人搬砖，一天十二小时，万元工资被克扣，生病就吃止疼药。 https://t.co/2WiKqbD26L",
    "images": "",
    "videos": "/tweet/video/whyyoutouzhele/2025/06/05/1930297242050801865_0.jpg,/tweet/video/whyyoutouzhele/2025/06/05/1930297242050801865_1.jpg,",
    "isReply": false,
    "isRetweet": false,
    "isSelfThread": false,
    "likes": 17,
    "replies": 2,
    "retweets": 0,
    "views": 3737,
    "originVideos": "https://video.twimg.com/amplify_video/1930296196699942912/vid/avc1/480x270/Q5Hx1_0MUuL6Ze7s.mp4,https://video.twimg.com/amplify_video/1930296241868414976/vid/avc1/320x568/h-h2djlTOoTK7wfQ.mp4"
  },
  {
    "id": "1930304791714115694",
    "accountId": "whyyoutouzhele",
    "sensitive": false,
    "name": "李老师不是你老师",
    "createdDate": "2025-06-05 00:45:00",
    "content": "6月4日，特朗普发推文称：“我喜欢中国的习主席，一直如此，将来也会如此，但他非常强硬，与他达成协议极其困难！！！” https://t.co/iXftYyLsZV",
    "images": "/tweet/image/whyyoutouzhele/2025/06/05/1930304791714115694_0.jpg,",
    "videos": "",
    "isReply": false,
    "isRetweet": false,
    "isSelfThread": false,
    "likes": 33,
    "replies": 13,
    "retweets": 1,
    "views": 9802,
    "originVideos": ""
  },
  {
    "id": "1930301017482002568",
    "accountId": "whyyoutouzhele",
    "sensitive": false,
    "name": "李老师不是你老师",
    "createdDate": "2025-06-05 00:30:00",
    "content": "6月4日，B站用户已经无法像往常一样在水手这首歌下纪念六四，B站对歌曲水手的MV的评论区进行了非常严格的控评，现在B站用户在六月份发布的评论都被删除，普通用户发布的文字评论甚至是表情符号也都被删除了，但是两年前六四当天用户们在水手MV下隐晦地发送表情符号纪念六四的评论还在，还有五十多个跟楼。\n之所以选择在水手这首歌的评论区内纪念六四，是因为那首最有名的六四歌曲《自由花》，《自由花》是香港支援中国民主运动联合会的歌曲，由周礼茂填词，寄调台湾歌手郑智化《水手》一曲。",
    "images": "/tweet/image/whyyoutouzhele/2025/06/05/1930301017482002568_0.jpg,/tweet/image/whyyoutouzhele/2025/06/05/1930301017482002568_1.jpg,",
    "videos": "",
    "isReply": false,
    "isRetweet": false,
    "isSelfThread": false,
    "likes": 78,
    "replies": 9,
    "retweets": 5,
    "views": 21751,
    "originVideos": ""
  },
  {
    "id": "1930299046083588504",
    "accountId": "whyyoutouzhele",
    "sensitive": false,
    "name": "李老师不是你老师",
    "createdDate": "2025-06-05 00:22:10",
    "content": "6月4日，淘宝上59式坦克模型已经无法搜到。 https://t.co/RgzIvjUt8Y",
    "images": "/tweet/image/whyyoutouzhele/2025/06/05/1930299046083588504_0.jpg,",
    "videos": "",
    "isReply": false,
    "isRetweet": false,
    "isSelfThread": false,
    "likes": 68,
    "replies": 9,
    "retweets": 5,
    "views": 25929,
    "originVideos": ""
  },
  {
    "id": "1930309390185247109",
    "accountId": "whyyoutouzhele",
    "sensitive": false,
    "name": "李老师不是你老师",
    "createdDate": "2025-06-05 01:03:16",
    "content": "食堂随机砍人事件发生后，有网友发现，在微博搜索“武汉大学”，会出现大量黄V账户推荐来武大赏樱的搜索结果。但武大的赏樱季在三月，六月没有樱花。网友怀疑赏樱微博是买来洗版的。不过，在大量赏樱微博中也夹杂有展示武大食堂饭菜的微博，怀疑是反串冲塔。 https://t.co/CuzYCuh5jJ",
    "images": "/tweet/image/whyyoutouzhele/2025/06/05/1930309390185247109_0.jpg,/tweet/image/whyyoutouzhele/2025/06/05/1930309390185247109_1.jpg,/tweet/image/whyyoutouzhele/2025/06/05/1930309390185247109_2.jpg,/tweet/image/whyyoutouzhele/2025/06/05/1930309390185247109_3.jpg,",
    "videos": "",
    "isReply": true,
    "isRetweet": false,
    "isSelfThread": false,
    "likes": 23,
    "replies": 0,
    "retweets": 1,
    "views": 3681,
    "originVideos": ""
  },
  {
    "id": "1930319892042985703",
    "accountId": "whyyoutouzhele",
    "sensitive": false,
    "name": "李老师不是你老师",
    "createdDate": "2025-06-05 01:45:00",
    "content": "2023年10月8日，湖南衡阳祁东县兴旺陶瓷厂发生事故，造成一个叫陈亮的员工死亡，该员工的遗体停在殡仪馆两年至今未处理，工厂不愿赔偿。据其家人描述，该工厂的安全管理存在漏洞，事发时无专业安全员施救，且工厂未主动联系家属，还指使工友串供。陈亮家人起诉工厂，法院判赔后工厂依旧拒偿。 https://t.co/VbnNrTtf7u",
    "images": "/tweet/image/whyyoutouzhele/2025/06/05/1930319892042985703_0.jpg,",
    "videos": "/tweet/video/whyyoutouzhele/2025/06/05/1930319892042985703_0.jpg,/tweet/video/whyyoutouzhele/2025/06/05/1930319892042985703_1.jpg,",
    "isReply": false,
    "isRetweet": false,
    "isSelfThread": false,
    "likes": 16,
    "replies": 3,
    "retweets": 1,
    "views": 6784,
    "originVideos": "https://video.twimg.com/amplify_video/1930304448951136256/vid/avc1/320x568/DpwLFRAwaj0ADZIf.mp4,https://video.twimg.com/amplify_video/1930304466252599296/vid/avc1/320x568/4-_t2yQs9ukXVtEs.mp4"
  },
  {
    "id": "1930316117601382502",
    "accountId": "whyyoutouzhele",
    "sensitive": false,
    "name": "李老师不是你老师",
    "createdDate": "2025-06-05 01:30:00",
    "content": "6月3日，越通社报道，越南修改《人口法令》，取消“一孩或二孩”生育规定。\n原规定“决定生育时间和间隔”被修改为：“个人或夫妻在平等基础上，根据年龄、健康状况、学习、工作、收入以及抚养子女的能力，自主决定生育时间、子女数量及每胎间隔时间”。同时，删除原第2款“每对夫妻只生育一个或两个孩子，特殊情况由政府另行规定”。\n越通社称，此次修改旨在解决各地区、各群体间生育率差异过大的问题，防止出生率过低、无法达到更替水平的情况出现。这可能对今后的经济、社会、国防和安全的可持续发展产生负面影响。",
    "images": "/tweet/image/whyyoutouzhele/2025/06/05/1930316117601382502_0.jpg,/tweet/image/whyyoutouzhele/2025/06/05/1930316117601382502_1.jpg,/tweet/image/whyyoutouzhele/2025/06/05/1930316117601382502_2.jpg,",
    "videos": "",
    "isReply": false,
    "isRetweet": false,
    "isSelfThread": false,
    "likes": 30,
    "replies": 7,
    "retweets": 1,
    "views": 19129,
    "originVideos": ""
  },
  {
    "id": "1930312342924849574",
    "accountId": "whyyoutouzhele",
    "sensitive": false,
    "name": "李老师不是你老师",
    "createdDate": "2025-06-05 01:15:00",
    "content": "6月4日，现任中国国民党主席朱立伦也在脸书上发文纪念六四运动，同时提醒民进党莫再为大罢免催票，操作国内对立。 https://t.co/3d6bIQ2yMa https://t.co/gIDn66lif2",
    "images": "/tweet/image/whyyoutouzhele/2025/06/05/1930312342924849574_0.jpg,/tweet/image/whyyoutouzhele/2025/06/05/1930312342924849574_1.jpg,",
    "videos": "",
    "isReply": false,
    "isRetweet": false,
    "isSelfThread": false,
    "likes": 57,
    "replies": 13,
    "retweets": 5,
    "views": 33327,
    "originVideos": ""
  },
  {
    "id": "1930323672897552675",
    "accountId": "whyyoutouzhele",
    "sensitive": false,
    "name": "李老师不是你老师",
    "createdDate": "2025-06-05 02:00:01",
    "content": "近日，抖音平台上“佳伟饿了”陷入了维权风波，起因是博主买的二手理想汽车发现轮胎静音棉损坏，找4s要求更换，但被拒绝，发在网上产生舆论风波后，理想在暗地里要求其删除视频，并给予补偿，被拒绝后又通过汽车定位找到车主，让车主佳伟陷入了极大的恐慌。同时，他的账号“佳伟饿了”被抖音禁止关注，其通过维权来获得的粉丝全部清除，6月2日，佳伟在“佳伟没了”发作品表示再也不碰汽车话题。",
    "images": "/tweet/image/whyyoutouzhele/2025/06/05/1930323672897552675_0.jpg,",
    "videos": "/tweet/video/whyyoutouzhele/2025/06/05/1930323672897552675_0.jpg,/tweet/video/whyyoutouzhele/2025/06/05/1930323672897552675_1.jpg,",
    "isReply": false,
    "isRetweet": false,
    "isSelfThread": false,
    "likes": 13,
    "replies": 7,
    "retweets": 1,
    "views": 5477,
    "originVideos": "https://video.twimg.com/amplify_video/1930300316483780614/vid/avc1/320x568/gdywvUWb-260aAUs.mp4,https://video.twimg.com/amplify_video/1930300316571897856/vid/avc1/320x568/-vilHl5s9GRi0oas.mp4"
  },
  {
    "id": "1930327441295454448",
    "accountId": "whyyoutouzhele",
    "sensitive": false,
    "name": "李老师不是你老师",
    "createdDate": "2025-06-05 02:15:00",
    "content": "6月4日，河北邯郸市水厂路光明路口发生路面塌陷，两辆汽车掉入大坑内，车内人员自己爬了出来。网友反映，这条路4月刚修完，上一次修是去年国庆后，不到一年修两次还能塌。目前，事故现场已被围挡起来。 https://t.co/I8hGNr5RWx",
    "images": "",
    "videos": "/tweet/video/whyyoutouzhele/2025/06/05/1930327441295454448_0.jpg,/tweet/video/whyyoutouzhele/2025/06/05/1930327441295454448_1.jpg,/tweet/video/whyyoutouzhele/2025/06/05/1930327441295454448_2.jpg,",
    "isReply": false,
    "isRetweet": false,
    "isSelfThread": false,
    "likes": 9,
    "replies": 2,
    "retweets": 2,
    "views": 3563,
    "originVideos": "https://video.twimg.com/amplify_video/1930309817014325248/vid/avc1/320x564/YfiH2ylsTWw_m8yJ.mp4,https://video.twimg.com/amplify_video/1930309817026940928/vid/avc1/320x568/3IGpQpO10LR86HNq.mp4,https://video.twimg.com/amplify_video/1930309817060458496/vid/avc1/320x568/q0e4OE7fEEvQfkWb.mp4"
  },
  {
    "id": "1930331971198304295",
    "accountId": "whyyoutouzhele",
    "sensitive": false,
    "name": "李老师不是你老师",
    "createdDate": "2025-06-05 02:33:00",
    "content": "6月2日，南昌海湾石油加油站因拖欠房东租金1.3亿被告上法庭，停止营业。此前，该加油站售卖加油充值卡充值卡每人1000-5000不等，有些公司卡达到上万，预计有10000多人充值却用不了，大量用户前往加油站维权。 https://t.co/WBp0blgwDo",
    "images": "/tweet/image/whyyoutouzhele/2025/06/05/1930331971198304295_0.jpg,/tweet/image/whyyoutouzhele/2025/06/05/1930331971198304295_1.jpg,/tweet/image/whyyoutouzhele/2025/06/05/1930331971198304295_2.jpg,/tweet/image/whyyoutouzhele/2025/06/05/1930331971198304295_3.jpg,",
    "videos": "",
    "isReply": false,
    "isRetweet": false,
    "isSelfThread": false,
    "likes": 18,
    "replies": 6,
    "retweets": 1,
    "views": 3100,
    "originVideos": ""
  },
  {
    "id": "1930338770370605357",
    "accountId": "whyyoutouzhele",
    "sensitive": false,
    "name": "李老师不是你老师",
    "createdDate": "2025-06-05 03:00:01",
    "content": "6月4日，贵州省遵义市道真县民生然气站，因为拖欠工资，愤怒的工人直接把铲车开上了门口的楼梯，直接把大厅的入口堵死了，博主表示2024年给他们干了整整一年，工资一分钱都没发。\n6月4日，中建八局，四川淮口人才公寓项目欠薪，工人们无奈堵门讨薪 。\n6月3日，广东深圳，中建深装负责的光明初级中学项目停工一个月，不给工人发工资和生活费。\n6月4日，江西教师发帖吐槽，教师边远地区补助拖欠半年了，网友跟帖，我们22年的还没发呢。",
    "images": "/tweet/image/whyyoutouzhele/2025/06/05/1930338770370605357_0.jpg,",
    "videos": "/tweet/video/whyyoutouzhele/2025/06/05/1930338770370605357_0.jpg,/tweet/video/whyyoutouzhele/2025/06/05/1930338770370605357_1.jpg,/tweet/video/whyyoutouzhele/2025/06/05/1930338770370605357_2.jpg,",
    "isReply": false,
    "isRetweet": false,
    "isSelfThread": false,
    "likes": 5,
    "replies": 3,
    "retweets": 1,
    "views": 2776,
    "originVideos": "https://video.twimg.com/amplify_video/1930300669371547651/vid/avc1/320x568/ylW5iO8k_EtC9qPd.mp4,https://video.twimg.com/amplify_video/1930300759041572868/vid/avc1/320x568/RLwH-ysSo721eBM-.mp4,https://video.twimg.com/amplify_video/1930301223078395913/vid/avc1/320x568/ZAKQbOAErZiD6OvR.mp4"
  },
  {
    "id": "1930346315457626176",
    "accountId": "whyyoutouzhele",
    "sensitive": false,
    "name": "李老师不是你老师",
    "createdDate": "2025-06-05 03:30:00",
    "content": "6月4日，河北石家庄一处施工现场发生坍塌事故，致三人死亡。河北省石家庄市应急管理局发布情况通报：系污水管道突然发生爆裂，造成基坑侧面土方及路面坍塌，导致3人被困最终死亡。 https://t.co/P7yZWOTLUa",
    "images": "/tweet/image/whyyoutouzhele/2025/06/05/1930346315457626176_0.jpg,",
    "videos": "/tweet/video/whyyoutouzhele/2025/06/05/1930346315457626176_0.jpg,",
    "isReply": false,
    "isRetweet": false,
    "isSelfThread": false,
    "likes": 2,
    "replies": 0,
    "retweets": 0,
    "views": 241,
    "originVideos": "https://video.twimg.com/amplify_video/1930302588995436544/vid/avc1/480x270/ZVO4dkpCZGDCBT-k.mp4"
  },
  {
    "id": "1930353867633389733",
    "accountId": "whyyoutouzhele",
    "sensitive": false,
    "name": "李老师不是你老师",
    "createdDate": "2025-06-05 04:00:00",
    "content": "网友投稿\n上海交通大学附属中学研学活动每人收取1658元，征询单上标注的是“自愿”，但是不参加活动的学生由于拿不到相关学分，将面临无法毕业的风险。\n学生普遍反映，有校方人员进入班级，以“没有团结感和集体感”为由指责不参与此次研学的学生。 https://t.co/RJKHWUH0M7",
    "images": "/tweet/image/whyyoutouzhele/2025/06/05/1930353867633389733_0.jpg,/tweet/image/whyyoutouzhele/2025/06/05/1930353867633389733_1.jpg,",
    "videos": "",
    "isReply": false,
    "isRetweet": false,
    "isSelfThread": false,
    "likes": 9,
    "replies": 3,
    "retweets": 0,
    "views": 2465,
    "originVideos": ""
  },
  {
    "id": "1930361415061143571",
    "accountId": "whyyoutouzhele",
    "sensitive": false,
    "name": "李老师不是你老师",
    "createdDate": "2025-06-05 04:30:00",
    "content": "6月4日，博主表示，自己在武汉一家民营的二级医院，基本工资都没有。\n6月3日，山东潍坊昌乐学校，一博主发帖吐槽，一年多没发工资了，我都佩服我自己怎么坚持下来的。 https://t.co/k3FIcPwMG2",
    "images": "/tweet/image/whyyoutouzhele/2025/06/05/1930361415061143571_0.jpg,/tweet/image/whyyoutouzhele/2025/06/05/1930361415061143571_1.jpg,/tweet/image/whyyoutouzhele/2025/06/05/1930361415061143571_2.jpg,/tweet/image/whyyoutouzhele/2025/06/05/1930361415061143571_3.jpg,",
    "videos": "",
    "isReply": false,
    "isRetweet": false,
    "isSelfThread": false,
    "likes": 11,
    "replies": 2,
    "retweets": 1,
    "views": 2528,
    "originVideos": ""
  },
  {
    "id": "1930368935490457992",
    "accountId": "whyyoutouzhele",
    "sensitive": false,
    "name": "李老师不是你老师",
    "createdDate": "2025-06-05 04:59:53",
    "content": "现场画面： https://t.co/txWc3ucxik",
    "images": "",
    "videos": "/tweet/video/whyyoutouzhele/2025/06/05/1930368935490457992_0.jpg,",
    "isReply": true,
    "isRetweet": false,
    "isSelfThread": false,
    "likes": 0,
    "replies": 0,
    "retweets": 0,
    "views": 8,
    "originVideos": "https://video.twimg.com/amplify_video/1930368844003991552/vid/avc1/320x568/g0Iv5Eh67DL6gDCm.mp4"
  }
]