[{"id":1772087583000,"createdDate":"2026-02-26 06:33","name":"英国广播公司","title":"比爾·蓋茨據報承認與兩俄羅斯女性有染並道歉  梅琳達稱想起「令人痛苦的時光」","content":"美國媒體報導，在兩人分手之前，梅琳達已對丈夫和愛潑斯坦之間的往來感到不安。兩人宣布分手後，比爾・蓋茨承認自己曾在2019年與一名微軟員工有婚外情。","newsLink":"https://www.bbc.com/zhongwen/articles/c70k8k9vjxyo/trad?at_medium=RSS&at_campaign=rss","thumbnail":"","detailImage":"news/detail/bbc/2026/02/26/1772087583000.webp","sourceId":"bbc"},{"id":1772087264000,"createdDate":"2026-02-26 06:27","name":"英国广播公司","title":"法輪功團體神韻藝術團巡演引發針對澳洲總理官邸的炸彈威脅","content":"該團體被警告若不取消演出，將會有人在安東尼·阿爾巴尼斯的住所引爆炸藥。","newsLink":"https://www.bbc.com/zhongwen/articles/c8egxg8p5g6o/trad?at_medium=RSS&at_campaign=rss","thumbnail":"","detailImage":"news/detail/bbc/2026/02/26/1772087264000.webp","sourceId":"bbc"},{"id":1772083761000,"createdDate":"2026-02-26 05:29","name":"英国广播公司","title":"黎智英欺詐案上訴得直：定罪及刑罰被撤銷，出獄時間提前","content":"黎智英正就國安案被判囚20年，由於欺詐刑期被撤銷，坐牢時間有所縮減，但仍要服刑至2040年。","newsLink":"https://www.bbc.com/zhongwen/articles/c9dnxn569epo/trad?at_medium=RSS&at_campaign=rss","thumbnail":"","detailImage":"news/detail/bbc/2026/02/26/1772083761000.webp","sourceId":"bbc"},{"id":1772083678000,"createdDate":"2026-02-26 05:27","name":"英国广播公司","title":"我們需要對AI機器人保持禮貌嗎？","content":"與中文和英文相比，如果你對日文聊天機器人過於客氣，它們的表現反而會略遜一籌。","newsLink":"https://www.bbc.com/zhongwen/articles/crk8jrx52n7o/trad?at_medium=RSS&at_campaign=rss","thumbnail":"","detailImage":"news/detail/bbc/2026/02/26/1772083678000.webp","sourceId":"bbc"},{"id":1772082763000,"createdDate":"2026-02-26 05:12","name":"英国广播公司","title":"「像鬼一樣工作」：台灣外籍移工為何陷入「強迫勞動」處境","content":"台灣不少外籍移工因為債務纏身，而落入國際定義的「強迫勞動」。多名移工接受BBC中文訪談，有人經歷工傷，仍不敢停止工作；也有人被仲介收取高額仲介費和買工費，陷入債上加債的循環。","newsLink":"https://www.bbc.com/zhongwen/articles/c8r1ekpkky0o/trad?at_medium=RSS&at_campaign=rss","thumbnail":"","detailImage":"news/detail/bbc/2026/02/26/1772082763000.webp","sourceId":"bbc"},{"id":1772076889000,"createdDate":"2026-02-26 03:34","name":"英国广播公司","title":"特朗普國情咨文報告事實查核：失業率、物價、戰爭調停及其它","content":"美國經濟與可負擔性是這次談話的核心主題。這也是數十年來最長的一次美國國會演說。特朗普也對非法移民，以及結束世界各地一系列戰爭等議題作出了多項主張。","newsLink":"https://www.bbc.com/zhongwen/articles/c0e5zrnqql8o/trad?at_medium=RSS&at_campaign=rss","thumbnail":"","detailImage":"news/detail/bbc/2026/02/26/1772076889000.webp","sourceId":"bbc"}]