[{"id":1758872681000,"createdDate":"2025-09-26 07:44","name":"法国国际广播电台","title":"香港蝉联全球最自由经济体 惟监管丶法制与财产权显着恶化","content":"香港在最新发布的《世界经济自由度2025年度报告》中，再获评为全球最自由经济体。港府凸显报告指香港在「国际贸易自由」蝉联首位，以及「稳健货币」和「监管」位列全球季军的成绩，但对报告指香港在过去七年的整体评分持续下跌，则只字不提，更以《港区国安法》实施有利香港来回应报告指《国安法》令香港在「监管」和「法律制度」方面显着恶化的问题。加拿大菲沙研究所每年均会发表《世界经济自由度》的年度报告，除了2023年外，香港有29年均位列全球最自由经济体首位。在最新一份报告中，香港亦继续位居榜首，但报告同时指出，香港的实际情况比单看名次更为复杂。","newsLink":"https://www.rfi.fr/cn/%E4%B8%AD%E5%9B%BD/20250926-%E9%A6%99%E6%B8%AF%E8%9D%89%E8%81%94%E5%85%A8%E7%90%83%E6%9C%80%E8%87%AA%E7%94%B1%E7%BB%8F%E6%B5%8E%E4%BD%93-%E6%83%9F%E7%9B%91%E7%AE%A1%E4%B8%B6%E6%B3%95%E5%88%B6%E4%B8%8E%E8%B4%A2%E4%BA%A7%E6%9D%83%E6%98%BE%E7%9D%80%E6%81%B6%E5%8C%96","thumbnail":"","detailImage":"news/detail/rfi/2025/09/26/1758872681000.webp","sourceId":"rfi"},{"id":1758904722000,"createdDate":"2025-09-26 16:38","name":"法国国际广播电台","title":"内塔尼亚胡在联大发言 抨击西方向哈马斯屈服 连线加沙扬声器向人质喊话","content":"内塔尼亚胡周五在联大发言称，建立巴勒斯坦国对以色列而言是“民族自杀”。他抨击承认巴勒斯坦国的西方国家向哈马斯“屈服”，证明“杀犹太人能得回报”，驳斥加沙地带发生“种族灭绝”的指控，承诺将“完成”对加沙地带哈马斯的打击。","newsLink":"https://www.rfi.fr/cn/%E5%9B%BD%E9%99%85/20250926-%E5%86%85%E5%A1%94%E5%B0%BC%E4%BA%9A%E8%83%A1%E5%9C%A8%E8%81%94%E5%A4%A7%E5%8F%91%E8%A8%80-%E6%8A%A8%E5%87%BB%E8%A5%BF%E6%96%B9%E5%90%91%E5%93%88%E9%A9%AC%E6%96%AF%E5%B1%88%E6%9C%8D-%E8%BF%9E%E7%BA%BF%E5%8A%A0%E6%B2%99%E6%89%AC%E5%A3%B0%E5%99%A8%E5%90%91%E4%BA%BA%E8%B4%A8%E5%96%8A%E8%AF%9D","thumbnail":"","detailImage":"news/detail/rfi/2025/09/26/1758904722000.webp","sourceId":"rfi"},{"id":1758903694000,"createdDate":"2025-09-26 16:21","name":"法国国际广播电台","title":"贝宁-法文拼字游戏竞赛强国","content":"在加拿大魁北克举行第53届法文拼字游戏（leScrabble）世界锦标赛上，本台[法广俱乐部]（ClubRFI）在非洲的伙伴机构[贝宁法文拼字游戏联合会]（FeBeSc）旗下的选手今年（2025年）再度赢得世界亚军。请听尼古拉的介绍。","newsLink":"https://www.rfi.fr/cn/%E9%9D%9E%E6%B4%B2/20250926-rfi-%E6%B3%95%E5%B9%BF%E4%B8%AD%E6%96%87-%E5%B0%BC%E5%8F%A4%E6%8B%89-%E9%9D%9E%E6%B4%B2-%E8%B4%9D%E5%AE%81-%E6%B3%95%E6%96%87%E6%8B%BC%E5%AD%97%E6%B8%B8%E6%88%8F%E7%AB%9E%E8%B5%9B%E5%BC%BA%E5%9B%BD","thumbnail":"","detailImage":"news/detail/rfi/2025/09/26/1758903694000.webp","sourceId":"rfi"},{"id":1758902948000,"createdDate":"2025-09-26 16:09","name":"法国国际广播电台","title":"在纽约联合国 中国和法国成为意想不到的气候科学捍卫者","content":"在纽约联合国，中国和法国成为意想不到的气候科学捍卫者。中国主席习近平在美国总统唐纳德·特朗普发表支持石油和化石燃料演讲后，发表了一个引人注目的声明：中国公布了到2035年减少温室气体排放的第一个量化目标，同时倡导可再生能源。而可再生能源项目曾遭到美国总统的大力谴责。","newsLink":"https://www.rfi.fr/cn/%E4%B8%AD%E5%9B%BD/20250926-%E5%9C%A8%E7%BA%BD%E7%BA%A6%E8%81%94%E5%90%88%E5%9B%BD-%E4%B8%AD%E5%9B%BD%E5%92%8C%E6%B3%95%E5%9B%BD%E6%88%90%E4%B8%BA%E6%84%8F%E6%83%B3%E4%B8%8D%E5%88%B0%E7%9A%84%E6%B0%94%E5%80%99%E7%A7%91%E5%AD%A6%E6%8D%8D%E5%8D%AB%E8%80%85","thumbnail":"","detailImage":"news/detail/rfi/2025/09/26/1758902948000.webp","sourceId":"rfi"},{"id":1758898873000,"createdDate":"2025-09-26 15:01","name":"法国国际广播电台","title":"【视频】丹麦一周两次无人机侵扰引安全担忧","content":"北欧国家丹麦本周以来接连发生两次不明无人机侵扰、导致机场被迫暂时关闭事件，引发公众的担忧。在哥本哈根，一些市民表示，事件令人不安，政府亟需给予切实有效的回应。","newsLink":"https://www.rfi.fr/cn/%E6%AC%A7%E6%B4%B2/20250926-%E8%A7%86%E9%A2%91-%E4%B8%B9%E9%BA%A6%E4%B8%80%E5%91%A8%E4%B8%A4%E6%AC%A1%E6%97%A0%E4%BA%BA%E6%9C%BA%E4%BE%B5%E6%89%B0%E5%BC%95%E5%AE%89%E5%85%A8%E6%8B%85%E5%BF%A7","thumbnail":"","detailImage":"news/detail/rfi/2025/09/26/1758898873000.webp","sourceId":"rfi"},{"id":1758898293000,"createdDate":"2025-09-26 14:51","name":"法国国际广播电台","title":"特朗普宣布新关税：药品高达100%","content":"美国总统特朗普周四宣布新关税措施，包括卡车，家具和药品，其中对药品”征收100%的进口关税。","newsLink":"https://www.rfi.fr/cn/%E5%9B%BD%E9%99%85/20250926-%E7%89%B9%E6%9C%97%E6%99%AE%E5%AE%A3%E5%B8%83%E6%96%B0%E5%85%B3%E7%A8%8E-%E8%8D%AF%E5%93%81%E9%AB%98%E8%BE%BE100","thumbnail":"","detailImage":"news/detail/rfi/2025/09/26/1758898293000.webp","sourceId":"rfi"},{"id":1758896727000,"createdDate":"2025-09-26 14:25","name":"法国国际广播电台","title":"丹麦再出现来源不明无人机 一座机场临时关闭","content":"丹麦一座新机场因连续两晚遭无人机入侵而于周四至周五凌晨被迫关闭。哥本哈根方面称，自本周初以来，该地区正遭受来源不明的“混合攻击”，全国处于高度戒备状态。","newsLink":"https://www.rfi.fr/cn/%E5%9B%BD%E9%99%85/20250926-%E4%B8%B9%E9%BA%A6%E5%86%8D%E5%87%BA%E7%8E%B0%E6%9D%A5%E6%BA%90%E4%B8%8D%E6%98%8E%E6%97%A0%E4%BA%BA%E6%9C%BA-%E4%B8%80%E5%BA%A7%E6%9C%BA%E5%9C%BA%E4%B8%B4%E6%97%B6%E5%85%B3%E9%97%AD","thumbnail":"","detailImage":"news/detail/rfi/2025/09/26/1758896727000.webp","sourceId":"rfi"},{"id":1758894108000,"createdDate":"2025-09-26 13:41","name":"法国国际广播电台","title":"视频 意大利和西班牙派出船只保护驶往加沙运送物资船队","content":"意大利和西班牙今天派出海军舰队保护前往加沙运送人道救援物资的船队，这个名叫LeFurorP46的有来自45个国家船只组成的船队，曾经本周三24日遭受无人机袭击，请看视频报道。","newsLink":"https://www.rfi.fr/cn/%E4%B8%AD%E4%B8%9C/20250926-%E8%A7%86%E9%A2%91-%E6%84%8F%E5%A4%A7%E5%88%A9%E5%92%8C%E8%A5%BF%E7%8F%AD%E7%89%99%E6%B4%BE%E5%87%BA%E8%88%B9%E5%8F%AA%E4%BF%9D%E6%8A%A4%E9%A9%B6%E5%BE%80%E5%8A%A0%E6%B2%99%E8%BF%90%E9%80%81%E7%89%A9%E8%B5%84%E8%88%B9%E9%98%9F","thumbnail":"","detailImage":"news/detail/rfi/2025/09/26/1758894108000.webp","sourceId":"rfi"},{"id":1758893658000,"createdDate":"2025-09-26 13:34","name":"法国国际广播电台","title":"联合国锁定158家在巴勒斯坦领土上的以色列定居点开展业务的公司","content":"联合国周五发布了期待已久的更新版数据库，数据库列出了来自11个国家的158家公司, 它们是在巴勒斯坦领土上的以色列定居点开展业务的公司。法新社报道，联合国人权事务高级专员沃尔克·图尔克谴责以色列在被占领的约旦河西岸巴勒斯坦领土上建立定居点的政策，说这是是战争罪。","newsLink":"https://www.rfi.fr/cn/%E5%9B%BD%E9%99%85/20250926-%E8%81%94%E5%90%88%E5%9B%BD%E9%94%81%E5%AE%9A158%E5%AE%B6%E5%9C%A8%E5%B7%B4%E5%8B%92%E6%96%AF%E5%9D%A6%E9%A2%86%E5%9C%9F%E4%B8%8A%E7%9A%84%E4%BB%A5%E8%89%B2%E5%88%97%E5%AE%9A%E5%B1%85%E7%82%B9%E5%BC%80%E5%B1%95%E4%B8%9A%E5%8A%A1%E7%9A%84%E5%85%AC%E5%8F%B8","thumbnail":"","detailImage":"news/detail/rfi/2025/09/26/1758893658000.webp","sourceId":"rfi"},{"id":1758889733000,"createdDate":"2025-09-26 12:28","name":"法国国际广播电台","title":"独立调查揭露：中国渔船在阿根廷海域非法捕捞继续有增无减","content":"总部位于英国伦敦的环境正义基金会(EnvironmentalJusticeFoundation)九月中旬发表了一份有关南美国家阿根廷毗邻专属经济区临近海域的非法捕捞船只的调查报告。报告引用来自全球渔业监测系统对自动识别系统(AIS)数据指出，在2019至2024年间，每年平均有343艘鱿鱼船在当地作业。而且，实际船队规模可能远远超出这一数字。除在201海里作业的鱿鱼船队外，该区域还存在规模可观的拖网船队，这些拖网船也同样大量捕捞一种被叫做阿根廷短鳍鱿的当地鱿鱼。根据全球渔业监测数据，中国籍渔船在其中占绝大部分，（74.6%），其后便是台湾地区（18.0%）和韩国（6.7%）","newsLink":"https://www.rfi.fr/cn/%E4%B8%93%E6%A0%8F%E6%A3%80%E7%B4%A2/%E7%8E%AF%E5%A2%83%E4%B8%8E%E5%8F%91%E5%B1%95/20250926-%E7%8B%AC%E7%AB%8B%E8%B0%83%E6%9F%A5%E6%8F%AD%E9%9C%B2-%E4%B8%AD%E5%9B%BD%E6%B8%94%E8%88%B9%E5%9C%A8%E9%98%BF%E6%A0%B9%E5%BB%B7%E6%B5%B7%E5%9F%9F%E9%9D%9E%E6%B3%95%E6%8D%95%E6%8D%9E%E7%BB%A7%E7%BB%AD%E6%9C%89%E5%A2%9E%E6%97%A0%E5%87%8F","thumbnail":"","detailImage":"news/detail/rfi/2025/09/26/1758889733000.webp","sourceId":"rfi"},{"id":1758888464000,"createdDate":"2025-09-26 12:07","name":"法国国际广播电台","title":"东帝汶民众抗议迫使议会取消议员终身养老金并放弃配车计划","content":"东帝汶议会周五回应民众愤怒，废除了2006年的一项法律，该法规定前议员、前总统、前总理和前部长享受终身养老金。","newsLink":"https://www.rfi.fr/cn/%E5%9B%BD%E9%99%85/20250926-%E4%B8%9C%E5%B8%9D%E6%B1%B6%E6%B0%91%E4%BC%97%E6%8A%97%E8%AE%AE%E8%BF%AB%E4%BD%BF%E8%AE%AE%E4%BC%9A%E5%8F%96%E6%B6%88%E8%AE%AE%E5%91%98%E7%BB%88%E8%BA%AB%E5%85%BB%E8%80%81%E9%87%91%E5%B9%B6%E6%94%BE%E5%BC%83%E9%85%8D%E8%BD%A6%E8%AE%A1%E5%88%92","thumbnail":"","detailImage":"news/detail/rfi/2025/09/26/1758888464000.webp","sourceId":"rfi"},{"id":1758884239000,"createdDate":"2025-09-26 10:57","name":"法国国际广播电台","title":"【视频】萨科齐被判刑5年：巴黎市民反应不一","content":"法国前总统萨科齐因利比亚竞选资金案涉“刑事共谋”被判处五年监禁，在法院周四（9月25日）宣判当天，巴黎市民向路透社在街头采访的记者表达了不同看法。","newsLink":"https://www.rfi.fr/cn/%E6%B3%95%E5%9B%BD/20250926-%E8%A7%86%E9%A2%91-%E8%90%A8%E7%A7%91%E9%BD%90%E8%A2%AB%E5%88%A4%E5%88%91-%E5%B7%B4%E9%BB%8E%E5%B8%82%E6%B0%91%E5%8F%8D%E5%BA%94%E4%B8%8D%E4%B8%80","thumbnail":"","detailImage":"news/detail/rfi/2025/09/26/1758884239000.webp","sourceId":"rfi"},{"id":1758883406000,"createdDate":"2025-09-26 10:43","name":"法国国际广播电台","title":"视频 : 美国前联邦调查局局长科米被起诉","content":"美国前联邦调查局局长科米曾经在2016年调查特朗普首次选举与俄罗斯关系，美国司法部在9月25日对其起诉，被指控涉嫌妨碍司法公正，请看视频报道。","newsLink":"https://www.rfi.fr/cn/%E6%94%BF%E6%B2%BB/20250926-%E8%A7%86%E9%A2%91-%E7%BE%8E%E5%9B%BD%E5%89%8D%E8%81%94%E9%82%A6%E8%B0%83%E6%9F%A5%E5%B1%80%E5%B1%80%E9%95%BF%E7%A7%91%E7%B1%B3%E8%A2%AB%E8%B5%B7%E8%AF%89","thumbnail":"","detailImage":"news/detail/rfi/2025/09/26/1758883406000.webp","sourceId":"rfi"},{"id":1758877188000,"createdDate":"2025-09-26 08:59","name":"法国国际广播电台","title":"台湾立法院院长韩国瑜率团访日与近70名日本议员交流","content":"台湾立法院院长韩国瑜率领的跨党派立法委员（国会议员）代表团，25日下午访问了东京永田町的众议院第一议员会馆，会见了以日华议员恳谈会（简称“日华恳”）会长、众议员议员古屋圭司为首的68名日本国会议员。古屋表示，希望在10月10日中华民国国庆日的庆典上，日华恳能够再次派出“世界最大规模”的访问团访问台北。","newsLink":"https://www.rfi.fr/cn/%E4%B8%AD%E5%9B%BD/20250926-%E5%8F%B0%E6%B9%BE%E7%AB%8B%E6%B3%95%E9%99%A2%E9%99%A2%E9%95%BF%E9%9F%A9%E5%9B%BD%E7%91%9C%E7%8E%87%E5%9B%A2%E8%AE%BF%E6%97%A5%E4%B8%8E%E8%BF%9170%E5%90%8D%E6%97%A5%E6%9C%AC%E8%AE%AE%E5%91%98%E4%BA%A4%E6%B5%81","thumbnail":"","detailImage":"news/detail/rfi/2025/09/26/1758877188000.webp","sourceId":"rfi"},{"id":1758876928000,"createdDate":"2025-09-26 08:55","name":"法国国际广播电台","title":"美国：特朗普的“眼中钉”  前FBI局长科米被控“严重罪行”","content":"美国司法部周四（9月25号）对前联邦调查局局长詹姆斯·科米（JamesComey）提起刑事指控，他被指控涉嫌妨碍司法公正。一旦罪名成立，可能面临最高五年监禁。","newsLink":"https://www.rfi.fr/cn/%E7%BE%8E%E6%B4%B2/20250926-%E7%BE%8E%E5%9B%BD-%E7%89%B9%E6%9C%97%E6%99%AE%E7%9A%84-%E7%9C%BC%E4%B8%AD%E9%92%89-%E5%89%8Dfbi%E5%B1%80%E9%95%BF%E7%A7%91%E7%B1%B3%E8%A2%AB%E6%8E%A7-%E4%B8%A5%E9%87%8D%E7%BD%AA%E8%A1%8C","thumbnail":"","detailImage":"news/detail/rfi/2025/09/26/1758876928000.webp","sourceId":"rfi"},{"id":1758927049000,"createdDate":"2025-09-26 22:50","name":"法国国际广播电台","title":"在新疆，习近平向国内外表示其民族同化政策成功了","content":"在西藏之行后仅一个月，习近平再次亲临新疆，表示“稳定是神圣不可侵犯”，强调他在少数民族管理方面的核心理念--培育少数民族具有“强烈的中华民族意识”--是成功的。此行既展示经济社会发展成果，也向国内外表明边疆治理和民族同化政策已见成效。","newsLink":"https://www.rfi.fr/cn/%E4%B8%93%E6%A0%8F%E6%A3%80%E7%B4%A2/%E6%B3%95%E5%9B%BD%E4%B8%96%E7%95%8C%E6%8A%A5/20250926-%E5%9C%A8%E6%96%B0%E7%96%86%EF%BC%8C%E4%B9%A0%E8%BF%91%E5%B9%B3%E5%90%91%E5%9B%BD%E5%86%85%E5%A4%96%E8%A1%A8%E6%98%8E%E5%85%B6%E6%B0%91%E6%97%8F%E5%90%8C%E5%8C%96%E6%94%BF%E7%AD%96%E6%88%90%E5%8A%9F%E4%BA%86","thumbnail":"","detailImage":"news/detail/rfi/2025/09/26/1758927049000.webp","sourceId":"rfi"},{"id":1758925582000,"createdDate":"2025-09-26 22:26","name":"法国国际广播电台","title":"美媒：泽连斯基向美国要求“战斧”远程导弹 特朗普考虑中","content":"Axios报道称泽伦斯基向特朗普要求“战斧”飞弹，以迫使普京上谈判桌。与此同时，《华尔街日报》引述知情人士消息称，特朗普对此要求虽然没有明确答应，但是抱持开放态度。","newsLink":"https://www.rfi.fr/cn/%E4%B8%AD%E5%9B%BD/20250926-%E7%BE%8E%E5%AA%92-%E6%B3%BD%E8%BF%9E%E6%96%AF%E5%9F%BA%E5%90%91%E7%BE%8E%E5%9B%BD%E8%A6%81%E6%B1%82-%E6%88%98%E6%96%A7-%E8%BF%9C%E7%A8%8B%E5%AF%BC%E5%BC%B9-%E7%89%B9%E6%9C%97%E6%99%AE%E8%80%83%E8%99%91%E4%B8%AD","thumbnail":"","detailImage":"news/detail/rfi/2025/09/26/1758925582000.webp","sourceId":"rfi"},{"id":1758925097000,"createdDate":"2025-09-26 22:18","name":"法国国际广播电台","title":"以色列总理联大讲话否认种族灭绝 多数代表团离席","content":"以色列总理内塔尼亚胡周五在联大发表讲话时否认以军正在加沙进行种族灭绝，巴勒斯坦权力机构则反驳其“满口谎言”。","newsLink":"https://www.rfi.fr/cn/%E4%B8%AD%E5%9B%BD/20250926-%E4%BB%A5%E8%89%B2%E5%88%97%E6%80%BB%E7%90%86%E8%81%94%E5%A4%A7%E8%AE%B2%E8%AF%9D%E5%90%A6%E8%AE%A4%E7%A7%8D%E6%97%8F%E7%81%AD%E7%BB%9D-%E5%A4%9A%E6%95%B0%E4%BB%A3%E8%A1%A8%E5%9B%A2%E7%A6%BB%E5%B8%AD","thumbnail":"","detailImage":"news/detail/rfi/2025/09/26/1758925097000.webp","sourceId":"rfi"},{"id":1758923534000,"createdDate":"2025-09-26 21:52","name":"法国国际广播电台","title":"李强总理在美国的两种面孔","content":"这是中国总理李强首次出席联合国大会，也是中国总理差不多十年来首次访美。李强的姿态看起来比较谨慎，利用出席联合国大会的机会，与加拿大总理卡尼会面，与欧盟主席冯德莱恩会谈，但都相当低调。即使因为中国政府首次具体承诺减排目标引起外界关注，也由远在北京的中国领导人习近平远程宣布而非他这位政府首脑宣布。","newsLink":"https://www.rfi.fr/cn/%E4%B8%AD%E5%9B%BD/20250926-%E6%9D%8E%E5%BC%BA%E5%9C%A8%E7%BE%8E%E5%9B%BD%E7%9A%84%E4%B8%A4%E7%A7%8D%E9%9D%A2%E5%AD%94","thumbnail":"","detailImage":"news/detail/rfi/2025/09/26/1758923534000.webp","sourceId":"rfi"},{"id":1758922652000,"createdDate":"2025-09-26 21:37","name":"法国国际广播电台","title":"法国新总理勒科尔尼承诺十月初之前完成组阁","content":"法国新总理勒科尔尼表示，他将在“议会开会之前”任命新政府，即十月初之前完成组阁。他在《巴黎人报》周五发表的采访中作出了这一承诺，并排除了恢复财富税等措施的可能性。","newsLink":"https://www.rfi.fr/cn/%E6%B3%95%E5%9B%BD/20250926-%E6%B3%95%E5%9B%BD%E6%96%B0%E6%80%BB%E7%90%86%E5%8B%92%E7%A7%91%E5%B0%94%E5%B0%BC%E6%89%BF%E8%AF%BA%E5%8D%81%E6%9C%88%E5%88%9D%E4%B9%8B%E5%89%8D%E5%AE%8C%E6%88%90%E7%BB%84%E9%98%81","thumbnail":"","detailImage":"news/detail/rfi/2025/09/26/1758922652000.webp","sourceId":"rfi"},{"id":1758922639000,"createdDate":"2025-09-26 21:37","name":"法国国际广播电台","title":"特朗普拟推新关税措施 要求半导体“美产与进口各占一半”","content":"美国政府正在考虑一项新方案，要求半导体产品在美国本土制造与进口的比例达到1:1。如果企业未能实现“国内生产与海外进口各半”的目标，将面临关税惩罚。此举旨在降低美国对外国半导体的依赖。","newsLink":"https://www.rfi.fr/cn/%E4%B8%AD%E5%9B%BD/20250926-%E7%89%B9%E6%9C%97%E6%99%AE%E6%8B%9F%E6%8E%A8%E6%96%B0%E5%85%B3%E7%A8%8E%E6%8E%AA%E6%96%BD-%E8%A6%81%E6%B1%82%E5%8D%8A%E5%AF%BC%E4%BD%93-%E7%BE%8E%E4%BA%A7%E4%B8%8E%E8%BF%9B%E5%8F%A3%E5%90%84%E5%8D%A0%E4%B8%80%E5%8D%8A","thumbnail":"","detailImage":"news/detail/rfi/2025/09/26/1758922639000.webp","sourceId":"rfi"},{"id":1758922249000,"createdDate":"2025-09-26 21:30","name":"法国国际广播电台","title":"美国法院驳回大疆诉求 维持其列入涉军企业名单","content":"美国联邦法院周五（9月26日）裁定，中国无人机制造商大疆创新（DJI）败诉，维持其继续列入美国国防部所谓的“涉军企业名单”。","newsLink":"https://www.rfi.fr/cn/%E4%B8%AD%E5%9B%BD/20250926-%E7%BE%8E%E5%9B%BD%E6%B3%95%E9%99%A2%E9%A9%B3%E5%9B%9E%E5%A4%A7%E7%96%86%E8%AF%89%E6%B1%82-%E7%BB%B4%E6%8C%81%E5%85%B6%E5%88%97%E5%85%A5%E6%B6%89%E5%86%9B%E4%BC%81%E4%B8%9A%E5%90%8D%E5%8D%95","thumbnail":"","detailImage":"news/detail/rfi/2025/09/26/1758922249000.webp","sourceId":"rfi"},{"id":1758921999000,"createdDate":"2025-09-26 21:26","name":"法国国际广播电台","title":"李强联大发言：警告世界警惕“冷战思维”卷土重来","content":"中国总理李强周五(9月26日）在纽约联合国大会发表讲话，警告\"世界进入新的动荡变革期\"，\"单边主义、冷战思维捲土重来，国际规则秩序受到严重冲击\"，李强为多边主义和自由贸易辩护，同时间接对美国提出批评。","newsLink":"https://www.rfi.fr/cn/%E4%B8%AD%E5%9B%BD/20250926-%E6%9D%8E%E5%BC%BA%E8%81%94%E5%A4%A7%E5%8F%91%E8%A8%80-%E8%AD%A6%E5%91%8A%E4%B8%96%E7%95%8C%E8%AD%A6%E6%83%95-%E5%86%B7%E6%88%98%E6%80%9D%E7%BB%B4-%E5%8D%B7%E5%9C%9F%E9%87%8D%E6%9D%A5","thumbnail":"","detailImage":"news/detail/rfi/2025/09/26/1758921999000.webp","sourceId":"rfi"},{"id":1758921769000,"createdDate":"2025-09-26 21:22","name":"法国国际广播电台","title":"消息称\"字节跳动\"将继续在美版TikTok中扮演重要角色","content":"路透社援引知情人士透露，TikTok的中国母公司字节跳动将在美国业务的新架构中继续保持重要地位。根据目前讨论的方案，字节跳动将保留TikTok美国业务的所有权，但会将用户数据、内容和推荐算法的控制权交由一家新成立的合资企业负责。这一超出外界预期的安排意味着，字节跳动仍将在新的美国TikTok实体中保持显著参与度。美国众议院中国问题特别委员会主席穆勒纳尔周五表示，他将对字节跳动出售短视频应用TikTok美国资产的交易进行全面监督。","newsLink":"https://www.rfi.fr/cn/%E4%B8%AD%E5%9B%BD/20250926-%E6%B6%88%E6%81%AF%E7%A7%B0-%E5%AD%97%E8%8A%82%E8%B7%B3%E5%8A%A8-%E5%B0%86%E7%BB%A7%E7%BB%AD%E5%9C%A8%E7%BE%8E%E7%89%88tiktok%E4%B8%AD%E6%89%AE%E6%BC%94%E9%87%8D%E8%A6%81%E8%A7%92%E8%89%B2","thumbnail":"","detailImage":"news/detail/rfi/2025/09/26/1758921769000.webp","sourceId":"rfi"},{"id":1758921386000,"createdDate":"2025-09-26 21:16","name":"法国国际广播电台","title":"特朗普称加沙停火协议\"接近达成\" 人质或将很快获释","content":"美国总统特朗普周五(9月26日）表示，他即将敲定一项协议，以结束加沙战争并促成人质获释。特朗普计划于下周一在白宫会见以色列总理内塔尼亚胡。","newsLink":"https://www.rfi.fr/cn/%E4%B8%AD%E5%9B%BD/20250926-%E7%89%B9%E6%9C%97%E6%99%AE%E7%A7%B0%E5%8A%A0%E6%B2%99%E5%81%9C%E7%81%AB%E5%8D%8F%E8%AE%AE-%E6%8E%A5%E8%BF%91%E8%BE%BE%E6%88%90-%E4%BA%BA%E8%B4%A8%E6%88%96%E5%B0%86%E5%BE%88%E5%BF%AB%E8%8E%B7%E9%87%8A","thumbnail":"","detailImage":"news/detail/rfi/2025/09/26/1758921386000.webp","sourceId":"rfi"},{"id":1758907401000,"createdDate":"2025-09-26 17:23","name":"法国国际广播电台","title":"俄罗斯供应中国先进空降特种作战装备 助增夺岛能力","content":"中央社9月26日伦敦电：一批俄罗斯与中国内部文件和采购合约显示，俄方已展开为共军供应先进空降特种作战装备，数量和项目至少足以支撑一个营，俄方并提供人员训练、改装等服务。专家分析，相关合作特别有助共军提升夺岛作战能力。","newsLink":"https://www.rfi.fr/cn/%E5%9B%BD%E9%99%85/20250926-%E4%BF%84%E7%BD%97%E6%96%AF%E4%BE%9B%E5%BA%94%E4%B8%AD%E5%9B%BD%E5%85%88%E8%BF%9B%E7%A9%BA%E9%99%8D%E7%89%B9%E7%A7%8D%E4%BD%9C%E6%88%98%E8%A3%85%E5%A4%87-%E5%8A%A9%E5%A2%9E%E5%A4%BA%E5%B2%9B%E8%83%BD%E5%8A%9B","thumbnail":"","detailImage":"news/detail/rfi/2025/09/26/1758907401000.webp","sourceId":"rfi"},{"id":1758905972000,"createdDate":"2025-09-26 16:59","name":"法国国际广播电台","title":"北京呼吁美国公开、公平对待TikTok等企业","content":"中国周五表示，希望美国以“公开、公平”的方式对待TikTok及其他在美投资的中国企业。此前，美国总统特朗普签署政令，规定了社交媒体平台TikTok出售其美国业务的框架。","newsLink":"https://www.rfi.fr/cn/%E5%9B%BD%E9%99%85/20250926-%E5%8C%97%E4%BA%AC%E5%91%BC%E5%90%81%E7%BE%8E%E5%9B%BD%E5%85%AC%E5%BC%80-%E5%85%AC%E5%B9%B3%E5%AF%B9%E5%BE%85tiktok%E7%AD%89%E4%BC%81%E4%B8%9A","thumbnail":"","detailImage":"news/detail/rfi/2025/09/26/1758905972000.webp","sourceId":"rfi"}]