[{"id":1741881960000,"createdDate":"2025-03-13 16:06","name":"德国之声","title":"美国特使抵达莫斯科 泽连斯基：普京无意休战","content":"美国特使史蒂夫·维特科夫周四已抵达莫斯科。有消息称，他可能会与普京会面。乌克兰总统择连斯基则认为，俄罗斯对停火建议不做反应，是在试图延长战争。","newsLink":"https://www.dw.com/zh/美国特使抵达莫斯科-泽连斯基：普京无意休战/a-71915048?maca=chi-rss-chi-all-1127-rdf","thumbnail":"","detailImage":"news/detail/dw/2025/03/13/1741881960000.webp","sourceId":"dw"},{"id":1741880460000,"createdDate":"2025-03-13 15:41","name":"德国之声","title":"客座评论：“赵乐际事件”何以被民间放大解读","content":"中国两会已经结束，本次两会称得上中规中矩、波澜不惊。但在两会的最后两天，中共第三号人物、全国人大委员长赵乐际却连接缺席政协闭幕式以及本应由他做总结的人大闭幕式，算是一个意外插曲，一时间引起舆论的关注和猜想。","newsLink":"https://www.dw.com/zh/客座评论：-赵乐际事件-何以被民间放大解读/a-71914672?maca=chi-rss-chi-all-1127-rdf","thumbnail":"","detailImage":"news/detail/dw/2025/03/13/1741880460000.webp","sourceId":"dw"},{"id":1741878120000,"createdDate":"2025-03-13 15:02","name":"德国之声","title":"降低供应链成本：中远海运与德国BLG物流公司达成合作","content":"据《日经亚洲》报道，中国国有企业中国远洋海运控股与德国物流公司BLGLogistics建立合作伙伴关系，旨在降低中国汽车在欧洲市场的成本。","newsLink":"https://www.dw.com/zh/降低供应链成本：中远海运与德国blg物流公司达成合作/a-71913827?maca=chi-rss-chi-all-1127-rdf","thumbnail":"","detailImage":"news/detail/dw/2025/03/13/1741878120000.webp","sourceId":"dw"},{"id":1741875840000,"createdDate":"2025-03-13 14:24","name":"德国之声","title":"德国情报机构：新冠病毒更可能来自实验室泄露","content":"据德国媒体报道，德国情报部门早在2020年就提出新冠病毒极可能源于实验室泄露的观点，但德国两届政府均对这一评估保持沉默。","newsLink":"https://www.dw.com/zh/德国情报机构：新冠病毒更可能来自实验室泄露/a-71913423?maca=chi-rss-chi-all-1127-rdf","thumbnail":"","detailImage":"news/detail/dw/2025/03/13/1741875840000.webp","sourceId":"dw"},{"id":1741875780000,"createdDate":"2025-03-13 14:23","name":"德国之声","title":"俄：停火给乌克兰喘息机会 特朗普近日或与普京通话","content":"普京的外交政策顾问乌沙科夫称，美国提出的30天停火建议不过是给乌克兰一个喘息的机会。另据最新消息，华盛顿方面称，美国谈判特使维特科夫周四已抵达莫斯科。一名克里姆林宫顾问称，维特科夫可能与普京会晤。","newsLink":"https://www.dw.com/zh/俄：停火给乌克兰喘息机会-特朗普近日或与普京通话/a-71913439?maca=chi-rss-chi-all-1127-rdf","thumbnail":"","detailImage":"news/detail/dw/2025/03/13/1741875780000.webp","sourceId":"dw"},{"id":1741874460000,"createdDate":"2025-03-13 14:01","name":"德国之声","title":"媒体：华为的说客涉嫌向政治人物行贿","content":"比利时联邦检察机构周四（3月13日）表示，他们在一起与欧洲议会相关的腐败调查中逮捕了几名嫌疑人。当地媒体报道称，中国华为公司涉嫌向欧盟议员行贿。","newsLink":"https://www.dw.com/zh/媒体：华为的说客涉嫌向政治人物行贿/a-71913272?maca=chi-rss-chi-all-1127-rdf","thumbnail":"","detailImage":"news/detail/dw/2025/03/13/1741874460000.webp","sourceId":"dw"},{"id":1741871760000,"createdDate":"2025-03-13 13:16","name":"德国之声","title":"赖清德：中国是台湾的“境外敌对势力”","content":"台湾总统赖清德13日以“凝聚反并吞共识，因应中国统战渗透”为主题，召开国安高层会议，会后发表敞厅谈话，谈及多项应对中国的策略。","newsLink":"https://www.dw.com/zh/赖清德：中国是台湾的-境外敌对势力/a-71912312?maca=chi-rss-chi-all-1127-rdf","thumbnail":"","detailImage":"news/detail/dw/2025/03/13/1741871760000.webp","sourceId":"dw"},{"id":1741870140000,"createdDate":"2025-03-13 12:49","name":"德国之声","title":"滞留国际空间站的美国两名宇航员归期再度被推迟","content":"由于出现技术问题，NASA和SpaceX取消了原定于周三的Crew-10任务发射。","newsLink":"https://www.dw.com/zh/滞留国际空间站的美国两名宇航员归期再度被推迟/a-71911796?maca=chi-rss-chi-all-1127-rdf","thumbnail":"","detailImage":"news/detail/dw/2025/03/13/1741870140000.webp","sourceId":"dw"}]