[{"id":1781337240000,"createdDate":"2026-06-13 07:54","name":"德国之声","title":"市长认罪充当中国代理人 华裔社区忧心忡忡","content":"2024年，加州阿卡迪亚市的选民选出了该市历史上首个全部由亚裔组成的市议会。如今，其中一名轮值市长承认充当中国政府非法代理人。这在当地社区引发震荡。","newsLink":"https://www.dw.com/zh/市长认罪充当中国代理人-华裔社区忧心忡忡/a-77477451?maca=chi-rss-chi-all-1127-rdf","thumbnail":"","detailImage":"news/detail/dw/2026/06/13/1781337240000.webp","sourceId":"dw"},{"id":1781358480000,"createdDate":"2026-06-13 13:48","name":"德国之声","title":"德语媒体：中国或可远程瘫痪德国基础设施","content":"《法兰克福汇报》援引德国联邦政府对一份“小质询”的答复称，中国对德国关键基础设施的影响构成了高度的安全风险。《南德意志报》则关注中国城市家庭的育儿现实。","newsLink":"https://www.dw.com/zh/德语媒体：中国或可远程瘫痪德国基础设施/a-77537207?maca=chi-rss-chi-all-1127-rdf","thumbnail":"","detailImage":"news/detail/dw/2026/06/13/1781358480000.webp","sourceId":"dw"},{"id":1781357580000,"createdDate":"2026-06-13 13:33","name":"德国之声","title":"欧盟将启动乌克兰和摩尔多瓦首轮入盟谈判","content":"欧盟将于周一（6月16日）启动与乌克兰和摩尔多瓦入盟谈判的首轮磋商。两国须首先证明其司法和行政体系符合欧盟标准。","newsLink":"https://www.dw.com/zh/欧盟将启动乌克兰和摩尔多瓦首轮入盟谈判/a-77537180?maca=chi-rss-chi-all-1127-rdf","thumbnail":"","detailImage":"news/detail/dw/2026/06/13/1781357580000.webp","sourceId":"dw"},{"id":1781353500000,"createdDate":"2026-06-13 12:25","name":"德国之声","title":"美伊表示和平协议临近 霍尔木兹炮火仍在持续","content":"特朗普已经数十次宣称美伊和平协议即将达成，而本周的再次宣称得到了伊朗外长阿拉格奇的呼应，后者表示协议\"从未如此接近\"。尽管如此，霍尔木兹海峡的战斗仍在继续，全球经济依然受困。","newsLink":"https://www.dw.com/zh/美伊表示和平协议临近-霍尔木兹炮火仍在持续/a-77537071?maca=chi-rss-chi-all-1127-rdf","thumbnail":"","detailImage":"news/detail/dw/2026/06/13/1781353500000.webp","sourceId":"dw"},{"id":1781351820000,"createdDate":"2026-06-13 11:57","name":"德国之声","title":"王沪宁：两岸一家亲 陆委会：欺骗手法","content":"在6月13日于厦门举行的海峡论坛会议上，中国全国政协主席王沪宁强调两岸同属“一个中国”，并称“广大台湾乡亲克服阻碍踊跃参与会议、与大陆同胞共叙亲情”。台湾陆委会则回应说，这是北京对台湾的“假融合、真施压”的欺骗手法。","newsLink":"https://www.dw.com/zh/王沪宁：两岸一家亲-陆委会：欺骗手法/a-77535755?maca=chi-rss-chi-all-1127-rdf","thumbnail":"","detailImage":"news/detail/dw/2026/06/13/1781351820000.webp","sourceId":"dw"},{"id":1781347500000,"createdDate":"2026-06-13 10:45","name":"德国之声","title":"歐盟庇護新制上路 加速難民審查","content":"歐盟正式啟動新的庇護制度，未來部分庇護申請人將在邊境先接受審查並加快處理。這項改革旨在結束歐盟國家之間長達多年的爭議。","newsLink":"https://www.dw.com/zh/歐盟庇護新制上路-加速難民審查/a-77536903?maca=chi-rss-chi-all-1127-rdf","thumbnail":"","detailImage":"news/detail/dw/2026/06/13/1781347500000.webp","sourceId":"dw"},{"id":1781344980000,"createdDate":"2026-06-13 10:03","name":"德国之声","title":"委内瑞拉黑帮团伙\"阿拉瓜列车\"头目被击毙","content":"委内瑞拉黑帮团伙\"阿拉瓜列车\"头目弗洛雷斯在一次联合行动中被击毙。特朗普政府多次指控该黑帮是美国多个城市暴力事件和毒品交易的幕后主谋。","newsLink":"https://www.dw.com/zh/委内瑞拉黑帮团伙-阿拉瓜列车-头目被击毙/a-77536256?maca=chi-rss-chi-all-1127-rdf","thumbnail":"","detailImage":"news/detail/dw/2026/06/13/1781344980000.webp","sourceId":"dw"},{"id":1781344440000,"createdDate":"2026-06-13 09:54","name":"德国之声","title":"美国批准派拉蒙收购华纳兄弟探索","content":"娱乐巨头派拉蒙已获准以1100亿美元收购华纳兄弟探索，包括其子公司CNN。此举引发人们对媒体审查制度以及对美国娱乐业权力进一步集中的担忧。","newsLink":"https://www.dw.com/zh/美国批准派拉蒙收购华纳兄弟探索/a-77535733?maca=chi-rss-chi-all-1127-rdf","thumbnail":"","detailImage":"news/detail/dw/2026/06/13/1781344440000.webp","sourceId":"dw"}]