[
  {
    "id": "1994798515391008967",
    "accountId": "whyyoutouzhele",
    "sensitive": false,
    "name": "李老师不是你老师",
    "createdDate": "2025-11-30 00:00:00",
    "content": "网友投稿\n一位从柬埔寨园区逃回来的朋友提醒，如今那边绑架中国人的，往往也是中国人。希望大家务必提高警惕。",
    "images": "/tweet/image/whyyoutouzhele/2025/11/30/1994798515391008967_0.jpg,/tweet/image/whyyoutouzhele/2025/11/30/1994798515391008967_1.jpg,/tweet/image/whyyoutouzhele/2025/11/30/1994798515391008967_2.jpg,",
    "videos": "",
    "isReply": false,
    "isRetweet": false,
    "isSelfThread": false,
    "likes": 360,
    "replies": 55,
    "retweets": 58,
    "views": 0,
    "originVideos": ""
  },
  {
    "id": "1994929163996680279",
    "accountId": "whyyoutouzhele",
    "sensitive": false,
    "name": "李老师不是你老师",
    "createdDate": "2025-11-30 08:39:00",
    "content": "因發起大火追責聯署被捕的關靖豐曾說：\n「只要克服恐懼沒有東西是不能說的，政權如果得民心，\n亦沒有理由懼怕任何言論，面對小小代價，我更沒有理\n由噤聲。發聲本身，更證明真嘢可以唔怕講，因此我沒\n有理由後悔」\n—自其2023年六四相關刑事毁壞罪的法庭報道",
    "images": "/tweet/image/whyyoutouzhele/2025/11/30/1994929163996680279_0.jpg,/tweet/image/whyyoutouzhele/2025/11/30/1994929163996680279_1.jpg,/tweet/image/whyyoutouzhele/2025/11/30/1994929163996680279_2.jpg,",
    "videos": "",
    "isReply": false,
    "isRetweet": false,
    "isSelfThread": false,
    "likes": 21,
    "replies": 6,
    "retweets": 2,
    "views": 0,
    "originVideos": ""
  },
  {
    "id": "1994921577041842652",
    "accountId": "whyyoutouzhele",
    "sensitive": false,
    "name": "李老师不是你老师",
    "createdDate": "2025-11-30 08:09:00",
    "content": "11月28日晚，“大埔宏福苑火灾关注组”提出“有关香港火灾的四大诉求”，并发起联署。联署发起人之一 關靖豐Miles 在大埔墟站附近派发传单。\n29日晚，据《独立媒体》报道，他因涉嫌“煽动”被带回住所搜证，“大埔宏福苑火灾关注组”的社交媒体账号也已被关闭。该联署在被关闭前，已有逾一万个签名。",
    "images": "/tweet/image/whyyoutouzhele/2025/11/30/1994921577041842652_0.jpg,/tweet/image/whyyoutouzhele/2025/11/30/1994921577041842652_1.jpg,/tweet/image/whyyoutouzhele/2025/11/30/1994921577041842652_2.jpg,",
    "videos": "",
    "isReply": false,
    "isRetweet": false,
    "isSelfThread": false,
    "likes": 63,
    "replies": 22,
    "retweets": 6,
    "views": 0,
    "originVideos": ""
  },
  {
    "id": "1994919303095669013",
    "accountId": "whyyoutouzhele",
    "sensitive": false,
    "name": "李老师不是你老师",
    "createdDate": "2025-11-30 08:00:00",
    "content": "11 月 29 日，抖音上带有“习”字的广告和相关评论区，要么充斥着阴阳怪气的表情包嘲讽，要么评论区被清空，仅剩零星几条评论。",
    "images": "",
    "videos": "/tweet/video/whyyoutouzhele/2025/11/30/1994919303095669013_0.jpg,",
    "isReply": false,
    "isRetweet": false,
    "isSelfThread": false,
    "likes": 105,
    "replies": 25,
    "retweets": 1,
    "views": 0,
    "originVideos": "https://video.twimg.com/amplify_video/1994789611176894464/pl/NqbPihLBoeY3zKvL.m3u8?v=cfc"
  },
  {
    "id": "1994912759600091273",
    "accountId": "whyyoutouzhele",
    "sensitive": false,
    "name": "李老师不是你老师",
    "createdDate": "2025-11-30 07:34:00",
    "content": "后续：警车整夜守在滨崎步主题咖啡店门口。滨崎步的海报也被从门上撤了下来。",
    "images": "/tweet/image/whyyoutouzhele/2025/11/30/1994912759600091273_0.jpg,",
    "videos": "/tweet/video/whyyoutouzhele/2025/11/30/1994912759600091273_0.jpg,",
    "isReply": false,
    "isRetweet": false,
    "isSelfThread": false,
    "likes": 269,
    "replies": 45,
    "retweets": 23,
    "views": 0,
    "originVideos": "https://video.twimg.com/amplify_video/1994755406451666945/pl/6PlINC9mcaoZNwUN.m3u8?v=cfc"
  },
  {
    "id": "1994904205346381854",
    "accountId": "whyyoutouzhele",
    "sensitive": false,
    "name": "李老师不是你老师",
    "createdDate": "2025-11-30 07:00:00",
    "content": "11月28日，日本外务省官网发布消息称，《外交》期刊第94卷正式出版。本期专题聚焦“中国习近平政权的诸多考量”。\n该刊物由日本外务省外交史料馆发行，第 94 卷的开篇文章为一篇对谈，题为：《习近平体制：迈向个人独裁的政治力学》。",
    "images": "/tweet/image/whyyoutouzhele/2025/11/30/1994904205346381854_0.jpg,",
    "videos": "",
    "isReply": false,
    "isRetweet": false,
    "isSelfThread": false,
    "likes": 267,
    "replies": 47,
    "retweets": 21,
    "views": 0,
    "originVideos": ""
  },
  {
    "id": "1994889104853553405",
    "accountId": "whyyoutouzhele",
    "sensitive": false,
    "name": "李老师不是你老师",
    "createdDate": "2025-11-30 06:00:00",
    "content": "11月29日，江苏南通，一名女外卖员因路上摔倒导致眼镜丢失、手部擦伤，只能一边哭一边在地上寻找散落的外卖单据。",
    "images": "",
    "videos": "/tweet/video/whyyoutouzhele/2025/11/30/1994889104853553405_0.jpg,",
    "isReply": false,
    "isRetweet": false,
    "isSelfThread": false,
    "likes": 294,
    "replies": 38,
    "retweets": 32,
    "views": 0,
    "originVideos": "https://video.twimg.com/amplify_video/1994771036097667072/pl/fcZqRh6uv3VEDD3N.m3u8?v=918"
  },
  {
    "id": "1994888480087052568",
    "accountId": "whyyoutouzhele",
    "sensitive": false,
    "name": "李老师不是你老师",
    "createdDate": "2025-11-30 05:57:00",
    "content": "据纽约时报报道，早在2024年9月，香港宏福苑居民就已向市政府反映指出，维修工程中使用的材料可能不符合阻燃标准。\n但劳工处驳回了居民对防护网的担忧，随后又根据承建商提交的文件，告知居民施工材料符合消防要求。\n根据《纽约时报》看到的住户邮件，他们曾致函香港劳工处，指出这些防护网可能不符合阻燃标准。\n他们还提到了使用泡沫板的风险，曾经担任土木工程师、现为社会活动人士的潘焯鸿说，他与屋苑居民一起提出了这些关切。\n周五，市政府官员告诉记者，发泡胶板为高度易燃材料，助长了火势以惊人的速度蔓延。\n负责监管工作场所安全问题的劳工处在声明中承认，最初曾错误驳回居民对防护网的担忧，声称现有规定并不涵盖脚手架上所用材料的阻燃标准。其后又根据承建商宏业建筑工程有限公司提交的文件，告知居民施工现场材料符合消防安全要求。",
    "images": "/tweet/image/whyyoutouzhele/2025/11/30/1994888480087052568_0.jpg,",
    "videos": "",
    "isReply": false,
    "isRetweet": false,
    "isSelfThread": false,
    "likes": 288,
    "replies": 39,
    "retweets": 51,
    "views": 0,
    "originVideos": ""
  }
]