[
  {
    "id": "1906020883845845016",
    "accountId": "whyyoutouzhele",
    "sensitive": false,
    "name": "李老师不是你老师",
    "createdDate": "2025-03-30 00:29:25",
    "content": "3月28日(发布) 一名俄兵上战场前豪情万丈，并表示“要把乌克兰人赶出去” 结果上战场后他和几名队友被乌军揍到鼻青脸肿。他狼狈的说“我们被彻底打败了” “我全身都是伤，腿被击中了，到处都是弹片，我感觉胳膊都麻木了” https://t.co/dHtoqbal8O",
    "images": "",
    "videos": "/tweet/video/whyyoutouzhele/2025/03/30/1906020883845845016_0.jpg,",
    "isReply": false,
    "isRetweet": false,
    "isSelfThread": false,
    "likes": 0,
    "replies": 0,
    "retweets": 0,
    "views": 76,
    "originVideos": "https://video.twimg.com/ext_tw_video/1906019301544656897/pu/vid/avc1/320x564/rUSONn7hmN1WFb6D.mp4?tag=12"
  },
  {
    "id": "1906026652116906433",
    "accountId": "whyyoutouzhele",
    "sensitive": false,
    "name": "李老师不是你老师",
    "createdDate": "2025-03-30 00:52:20",
    "content": "3月29日(发布) 重庆市沙坪坝区区委书记祁美文，被人质疑早年为文科背景，是如何进入北京航空航天大学就读软件工程专业，并获得工程硕士学位的。 https://t.co/x2OdxANTH0",
    "images": "/tweet/image/whyyoutouzhele/2025/03/30/1906026652116906433_0.jpg,/tweet/image/whyyoutouzhele/2025/03/30/1906026652116906433_1.jpg,/tweet/image/whyyoutouzhele/2025/03/30/1906026652116906433_2.jpg,",
    "videos": "",
    "isReply": false,
    "isRetweet": false,
    "isSelfThread": false,
    "likes": 14,
    "replies": 3,
    "retweets": 6,
    "views": 3196,
    "originVideos": ""
  }
]