[{"id":1782380475000,"createdDate":"2026-06-25 09:41","name":"法国国际广播电台","title":"习近平的“足球梦”雄心勃勃，“龙之队”的表现却为何如此糟糕？","content":"大家好，欢迎收听法国报纸摘要，在华盛顿与德黑兰签署的谅解备忘录中，伊朗民众似乎被完全忽视了，成为今天6月25日《费加罗报》首页关注重点。据该报指出，伊朗民间社会将该协议视为一种背叛；战争加剧了伊朗人民的生活困境，德黑兰弥漫着“苦涩的情绪”，并同时提醒，制裁已经“迅速侵蚀了伊朗人的购买力”，并助长了抗议活动。与此同时，法国刚刚经历了有记录以来最闷热的两个夜晚，由于气候变暖，这种危险现象正日益频繁则是《解放报》的封面话题。此外继《十字架报》与《世界报》后，在世界杯小组赛收官之际《解放报》也将目光放到中国足球队上，登出报道解析，远大梦想之下奈何成绩惨不忍睹。","newsLink":"https://www.rfi.fr/cn/%E4%B8%93%E6%A0%8F%E6%A3%80%E7%B4%A2/%E6%B3%95%E5%9B%BD%E6%8A%A5%E7%BA%B8%E6%91%98%E8%A6%81/20260625-%E4%B9%A0%E8%BF%91%E5%B9%B3%E7%9A%84-%E8%B6%B3%E7%90%83%E6%A2%A6-%E9%9B%84%E5%BF%83%E5%8B%83%E5%8B%83%EF%BC%8C-%E9%BE%99%E4%B9%8B%E9%98%9F-%E7%9A%84%E8%A1%A8%E7%8E%B0%E5%8D%B4%E4%B8%BA%E4%BD%95%E5%A6%82%E6%AD%A4%E7%B3%9F%E7%B3%95","thumbnail":"","detailImage":"news/detail/rfi/2026/06/25/1782380475000.webp","sourceId":"rfi"},{"id":1782379076000,"createdDate":"2026-06-25 09:17","name":"法国国际广播电台","title":"世界杯球赛 南非爆冷门1比0胜韩国队","content":"在世界杯A组赛中24日南非队爆冷门以1比0胜韩国队，让南非对首次普及32强，南非队将于6月28日星期日晚上7点迎战加拿大队。","newsLink":"https://www.rfi.fr/cn/%E4%BA%9A%E6%B4%B2/20260625-%E4%B8%96%E7%95%8C%E6%9D%AF%E7%90%83%E8%B5%9B-%E5%8D%97%E9%9D%9E%E7%88%86%E5%86%B7%E9%97%A81%E6%AF%940%E8%83%9C%E9%9F%A9%E5%9B%BD%E9%98%9F","thumbnail":"","detailImage":"news/detail/rfi/2026/06/25/1782379076000.webp","sourceId":"rfi"},{"id":1782378641000,"createdDate":"2026-06-25 09:10","name":"法国国际广播电台","title":"中国商务部加强举报措施严控两用物项出口 被拘留两名日本人为富士电机职员","content":"中国商务部24日宣布，将设立关于战略矿产军民两用（Dual-Use）产品出口管制违法违规行为的举报窗口。商务部表示，此举旨在“发挥社会监督作用”，被认为是进一步加强严控稀土等出口的执法和监管力度的措施。而据多名相关人士透露，今年5月，在中国辽宁省大连市，当地海关部门拘留的两名日本人为日本大型电机企业富士电机的员工，其中至少一人在该公司中国当地法人任职。他们涉嫌试图将中国加强出口管制的稀土相关物品带出境外，因此可能被认定违反相关法律法规，涉嫌触犯“走私国家禁止进出口货物罪”。","newsLink":"https://www.rfi.fr/cn/%E4%B8%AD%E5%9B%BD/20260625-%E4%B8%AD%E5%9B%BD%E5%95%86%E5%8A%A1%E9%83%A8%E5%8A%A0%E5%BC%BA%E4%B8%BE%E6%8A%A5%E6%8E%AA%E6%96%BD%E4%B8%A5%E6%8E%A7%E4%B8%A4%E7%94%A8%E7%89%A9%E9%A1%B9%E5%87%BA%E5%8F%A3-%E8%A2%AB%E6%8B%98%E7%95%99%E4%B8%A4%E5%90%8D%E6%97%A5%E6%9C%AC%E4%BA%BA%E4%B8%BA%E5%AF%8C%E5%A3%AB%E7%94%B5%E6%9C%BA%E8%81%8C%E5%91%98","thumbnail":"","detailImage":"news/detail/rfi/2026/06/25/1782378641000.webp","sourceId":"rfi"},{"id":1782375481000,"createdDate":"2026-06-25 08:18","name":"法国国际广播电台","title":"美国政府致函各州和企业：警惕中国施压，鼓励深化对台合作","content":"路透社报道，美国国务院、农业部和商务部近日联合致函美国各州及企业，称尽管中国在试图阻止与台湾的接触，并歪曲美国的对台政策，但鼓励其仍应进一步扩大与台湾的交流合作。","newsLink":"https://www.rfi.fr/cn/%E5%9B%BD%E9%99%85/20260625-%E7%BE%8E%E5%9B%BD%E6%94%BF%E5%BA%9C%E8%87%B4%E5%87%BD%E5%90%84%E5%B7%9E%E5%92%8C%E4%BC%81%E4%B8%9A-%E8%AD%A6%E6%83%95%E4%B8%AD%E5%9B%BD%E6%96%BD%E5%8E%8B%EF%BC%8C%E9%BC%93%E5%8A%B1%E6%B7%B1%E5%8C%96%E5%AF%B9%E5%8F%B0%E5%90%88%E4%BD%9C","thumbnail":"","detailImage":"news/detail/rfi/2026/06/25/1782375481000.webp","sourceId":"rfi"},{"id":1782370764000,"createdDate":"2026-06-25 06:59","name":"法国国际广播电台","title":"三月内两宗 港独立书店被指售煽动書遭逮捕 创办人加控洗黑钱 人权观察批荒谬","content":"香港警队国安人员再次行动，搜查为独立书店提供另类书展场地的「猎人书店」，并拘捕书店创办人黄文萱和另一名男子，指他们涉嫌违反国安法例下的新煽动罪，是国安警继3月下旬以同样罪名拘捕另一独立书店「一拳书馆」负责人之後的第二宗。国际人权组织「人权观察」批评当局的拘捕行动荒谬，而北京加强对香港的管控，亦令香港失去其开放性和包容。","newsLink":"https://www.rfi.fr/cn/%E6%B8%AF%E6%BE%B3%E5%8F%B0/20260625-%E4%B8%89%E6%9C%88%E5%86%85%E4%B8%A4%E5%AE%97-%E6%B8%AF%E7%8B%AC%E7%AB%8B%E4%B9%A6%E5%BA%97%E8%A2%AB%E6%8C%87%E5%94%AE%E7%85%BD%E5%8A%A8%E6%9B%B8%E9%81%AD%E9%80%AE%E6%8D%95-%E5%88%9B%E5%8A%9E%E4%BA%BA%E5%8A%A0%E6%8E%A7%E6%B4%97%E9%BB%91%E9%92%B1-%E4%BA%BA%E6%9D%83%E8%A7%82%E5%AF%9F%E6%89%B9%E8%8D%92%E8%B0%AC","thumbnail":"","detailImage":"news/detail/rfi/2026/06/25/1782370764000.webp","sourceId":"rfi"},{"id":1782370452000,"createdDate":"2026-06-25 06:54","name":"法国国际广播电台","title":"美国杯葛澳门APEC旅游部长级会议 以示对领事签证规定的不满","content":"澳门现正举行亚太经济合作会议(APEC)的旅游部长会议及相关工作组会议，商讨旅游永续发展和合作交流，有来自21个成员国逾二百名代表参加。不过，美国杯葛会议，拒绝派员出席，藉此表达对中方拒绝让领事馆官员赶赴澳门为美国有需要的公民提供领事服务的不满。","newsLink":"https://www.rfi.fr/cn/%E6%B8%AF%E6%BE%B3%E5%8F%B0/20260625-%E7%BE%8E%E5%9B%BD%E6%9D%AF%E8%91%9B%E6%BE%B3%E9%97%A8apec%E6%97%85%E6%B8%B8%E9%83%A8%E9%95%BF%E7%BA%A7%E4%BC%9A%E8%AE%AE-%E4%BB%A5%E7%A4%BA%E5%AF%B9%E9%A2%86%E4%BA%8B%E7%AD%BE%E8%AF%81%E8%A7%84%E5%AE%9A%E7%9A%84%E4%B8%8D%E6%BB%A1","thumbnail":"","detailImage":"news/detail/rfi/2026/06/25/1782370452000.webp","sourceId":"rfi"}]