[{"id":1727224594000,"createdDate":"2024-09-25 00:36","name":"法国国际广播电台","title":"黎巴嫩外长称美国是“拯救我们的关键” 真主党据报促伊朗袭击以色列遭冷遇","content":"以色列周二对贝鲁特的空袭造成黎巴嫩真主党一名高级指挥官死亡，双方的跨境袭击加剧了人们对中东爆发全面战争的担忧，黎巴嫩外长称只有美国才能帮助结束战斗。黎巴嫩真主党周三凌晨证实，其导弹部队的负责人易卜拉欣·古拜希（IbrahimQubaisi）在以色列周二对贝鲁特的空袭中丧生，以方稍早时宣布了这一消息。","newsLink":"https://www.rfi.fr/cn/%E4%B8%AD%E4%B8%9C/20240925-%E9%BB%8E%E5%B7%B4%E5%AB%A9%E5%A4%96%E9%95%BF%E7%A7%B0%E7%BE%8E%E5%9B%BD%E6%98%AF-%E6%8B%AF%E6%95%91%E6%88%91%E4%BB%AC%E7%9A%84%E5%85%B3%E9%94%AE-%E7%9C%9F%E4%B8%BB%E5%85%9A%E6%8D%AE%E6%8A%A5%E4%BF%83%E4%BC%8A%E6%9C%97%E8%A2%AD%E5%87%BB%E4%BB%A5%E8%89%B2%E5%88%97%E9%81%AD%E5%86%B7%E9%81%87","thumbnail":"","detailImage":"news/detail/rfi/2024/09/25/1727224594000.webp","sourceId":"rfi"},{"id":1727222862000,"createdDate":"2024-09-25 00:07","name":"法国国际广播电台","title":"中国宣布对美国PVH集团展开调查","content":"中国周二宣布，对拥有CK和TommyHilfiger两个服装品牌的美国PVH集团展开调查，因为该集团对涉嫌侵犯人权的新疆棉花制品进行了“毫无根据的抵制”。","newsLink":"https://www.rfi.fr/cn/%E4%B8%AD%E5%9B%BD/20240925-%E4%B8%AD%E5%9B%BD%E5%AE%A3%E5%B8%83%E5%AF%B9%E7%BE%8E%E5%9B%BDpvh%E9%9B%86%E5%9B%A2%E5%B1%95%E5%BC%80%E8%B0%83%E6%9F%A5","thumbnail":"","detailImage":"news/detail/rfi/2024/09/25/1727222862000.webp","sourceId":"rfi"},{"id":1727226418000,"createdDate":"2024-09-25 01:06","name":"法国国际广播电台","title":"泽连斯基指俄罗斯只能被迫求和 马克龙警告伊朗总统勿继续对俄支持","content":"乌克兰总统泽连斯基(VolodymyrZelenskyy)周二在联合国安理会表示，仅靠谈判无法平息俄罗斯与乌克兰之间的战争，必须迫使莫斯科实现和平。泽连斯基寻求西方领导人支持他提出的“胜利计划”，以结束这场始于2022年2月俄罗斯发动全面入侵的战争。","newsLink":"https://www.rfi.fr/cn/%E5%9B%BD%E9%99%85/20240925-%E6%B3%BD%E8%BF%9E%E6%96%AF%E5%9F%BA%E6%8C%87%E4%BF%84%E7%BD%97%E6%96%AF%E5%8F%AA%E8%83%BD%E8%A2%AB%E8%BF%AB%E6%B1%82%E5%92%8C-%E9%A9%AC%E5%85%8B%E9%BE%99%E8%AD%A6%E5%91%8A%E4%BC%8A%E6%9C%97%E6%80%BB%E7%BB%9F%E5%8B%BF%E7%BB%A7%E7%BB%AD%E5%AF%B9%E4%BF%84%E6%94%AF%E6%8C%81","thumbnail":"","detailImage":"news/detail/rfi/2024/09/25/1727226418000.webp","sourceId":"rfi"}]