[{"id":1731241346000,"createdDate":"2024-11-10 12:22","name":"法国国际广播电台","title":"乌克兰对莫斯科发动大规模无人机袭击 3个机场航班暂停","content":"法新社消息，周日上午，莫斯科地区成为无人机袭击的目标，其规模是俄罗斯入侵乌克兰以来前所未见。据俄罗斯当局称，约有30架飞机被击落，一名妇女受伤。","newsLink":"https://www.rfi.fr/cn/%E5%9B%BD%E9%99%85/20241110-%E4%B9%8C%E5%85%8B%E5%85%B0%E5%AF%B9%E8%8E%AB%E6%96%AF%E7%A7%91%E5%8F%91%E5%8A%A8%E5%A4%A7%E8%A7%84%E6%A8%A1%E6%97%A0%E4%BA%BA%E6%9C%BA%E8%A2%AD%E5%87%BB-3%E4%B8%AA%E6%9C%BA%E5%9C%BA%E8%88%AA%E7%8F%AD%E6%9A%82%E5%81%9C","thumbnail":"","detailImage":"news/detail/rfi/2024/11/10/1731241346000.webp","sourceId":"rfi"},{"id":1731230524000,"createdDate":"2024-11-10 09:22","name":"法国国际广播电台","title":"路透独家：美国下令台积电停向中国出口AI应用先进芯片","content":"路透社引述知情人士透露，美国已下令台湾半导体制造公司台积电从周一（11月11号）开始停止向中国客户出售常用于人工智能应用的先进芯片。","newsLink":"https://www.rfi.fr/cn/%E5%8F%B0%E6%B9%BE/20241110-%E8%B7%AF%E9%80%8F%E7%8B%AC%E5%AE%B6-%E7%BE%8E%E5%9B%BD%E4%B8%8B%E4%BB%A4%E5%8F%B0%E7%A7%AF%E7%94%B5%E5%81%9C%E5%90%91%E4%B8%AD%E5%9B%BD%E5%87%BA%E5%8F%A3ai%E5%BA%94%E7%94%A8%E5%85%88%E8%BF%9B%E8%8A%AF%E7%89%87","thumbnail":"","detailImage":"news/detail/rfi/2024/11/10/1731230524000.webp","sourceId":"rfi"}]