[{"id":1759159810000,"createdDate":"2025-09-29 15:30","name":"美国之音","title":"美台关税谈判之际，美国农业高级官员访问台湾","content":"在华盛顿与台北正在就台湾输美商品的出口关税进行谈判之际，一名美国农业高级官员率领一个贸易代表团本周访问台湾，旨在为美国企业拓展贸易机遇，并推动美国农产品出口。","newsLink":"https://www.voachinese.com/a/senior-u-s-agriculture-official-visits-taiwan-amid-tariff-talks-20250929/8069774.html","thumbnail":"","detailImage":"news/detail/voa/2025/09/29/1759159810000.webp","sourceId":"voa"},{"id":1759185116000,"createdDate":"2025-09-29 22:31","name":"美国之音","title":"特朗普在获得以色列支持后提出美国结束加沙战争的计划，说哈马斯应该接受，否则将面临以色列的毁灭","content":"唐纳德·特朗普总统在白宫会见以色列总理并获得以色列的支持后，提出了一项结束以色列与哈马斯在加沙的战争的新计划。该计划要求这个巴勒斯坦恐怖组织释放剩余人质，并被一个由阿拉伯和穆斯林国家组成的联盟解除武装。","newsLink":"https://www.voachinese.com/a/trump-unveils-plan-to-end-israel-hamas-war-in-gaza-20250929/8069839.html","thumbnail":"","detailImage":"news/detail/voa/2025/09/29/1759185116000.webp","sourceId":"voa"}]