[{"id":1745555340000,"createdDate":"2025-04-25 04:29","name":"德国之声","title":"美中關稅談判羅生門 中國稱未與美協商","content":"各界持續關注美國總統川普是否將下調對華關稅，美中究竟是否開始談判程序卻變成一場「羅生門」。中國外交部週四否認中美正在進行談判的說法，但川普再次宣稱「一切都在積極進行」。","newsLink":"https://www.dw.com/zh/美中關稅談判羅生門-中國稱未與美協商/a-72343081?maca=chi-rss-chi-all-1127-rdf","thumbnail":"","detailImage":"news/detail/dw/2025/04/25/1745555340000.webp","sourceId":"dw"},{"id":1745548620000,"createdDate":"2025-04-25 02:37","name":"德国之声","title":"美軍艦再經過台海 中國稱全程跟監","content":"4月23日，川普第二次任內二度派遣美國軍艦經過台灣海峽。美國強調這符合國際法保障的航行自由；中國解放軍則批評其「公開炒作」。","newsLink":"https://www.dw.com/zh/美軍艦再經過台海-中國稱全程跟監/a-72342876?maca=chi-rss-chi-all-1127-rdf","thumbnail":"","detailImage":"news/detail/dw/2025/04/25/1745548620000.webp","sourceId":"dw"}]