[
  {
    "id": "1931384406817509760",
    "accountId": "whyyoutouzhele",
    "sensitive": false,
    "name": "李老师不是你老师",
    "createdDate": "2025-06-08 00:15:00",
    "content": "网友投稿\n南京瑞仪电子厂集中营式管理员工，恐吓员工生产，一人不达标，全部人都得跟着挨骂，被迫延迟下班。工人生病想请假，表示开医院证明，负责人不仅不批准，还叫这人滚蛋。工厂要求工人每天提前半小时开早会，迟到三次立刻辞退。还有人反映，工厂配发的连体衣又脏又臭，让人难以忍受。据网友描述，厂里还有很多新疆人，哈萨克族人在被强迫劳动。",
    "images": "/tweet/image/whyyoutouzhele/2025/06/08/1931384406817509760_0.jpg,/tweet/image/whyyoutouzhele/2025/06/08/1931384406817509760_1.jpg,/tweet/image/whyyoutouzhele/2025/06/08/1931384406817509760_2.jpg,/tweet/image/whyyoutouzhele/2025/06/08/1931384406817509760_3.jpg,",
    "videos": "",
    "isReply": false,
    "isRetweet": false,
    "isSelfThread": false,
    "likes": 10,
    "replies": 1,
    "retweets": 0,
    "views": 6648,
    "originVideos": ""
  },
  {
    "id": "1931382576674930956",
    "accountId": "whyyoutouzhele",
    "sensitive": false,
    "name": "李老师不是你老师",
    "createdDate": "2025-06-08 00:07:44",
    "content": "安徽公务员投稿\n6月6日，安徽下发了禁酒令和禁餐令，覆盖行政事业单位和国有企业全体职工，即日起三人以上外出就餐必须报备，期间不准饮酒。当地纪检委会手持人脸识别设备去各大饭店进行摸排。\n该通知由单位口头传达，没有任何纸质文件。\n从社交媒体上可以发现，近期全国各地政府均下达了类似要求 https://t.co/R5wSghTKtl",
    "images": "/tweet/image/whyyoutouzhele/2025/06/08/1931382576674930956_0.jpg,/tweet/image/whyyoutouzhele/2025/06/08/1931382576674930956_1.jpg,/tweet/image/whyyoutouzhele/2025/06/08/1931382576674930956_2.jpg,/tweet/image/whyyoutouzhele/2025/06/08/1931382576674930956_3.jpg,",
    "videos": "",
    "isReply": false,
    "isRetweet": false,
    "isSelfThread": false,
    "likes": 27,
    "replies": 12,
    "retweets": 0,
    "views": 10761,
    "originVideos": ""
  },
  {
    "id": "1931380634758627632",
    "accountId": "whyyoutouzhele",
    "sensitive": false,
    "name": "李老师不是你老师",
    "createdDate": "2025-06-08 00:00:01",
    "content": "6月7日，一名医生博主吐槽由于医院降薪，医护人员只能下班后去兼职增加收入。\n6月7日，一博主发帖吐槽：广东化州市所有的医院都发不出工资了？化州市人民医院那个爱搭不理的态度，主治医师一天出现一次，询问一些问题爱搭不理，有事找不到人叫护士打电话沟通人也不出现，患者还是脑出血的情况。 https://t.co/TnuYMN7SSs",
    "images": "/tweet/image/whyyoutouzhele/2025/06/08/1931380634758627632_0.jpg,/tweet/image/whyyoutouzhele/2025/06/08/1931380634758627632_1.jpg,",
    "videos": "/tweet/video/whyyoutouzhele/2025/06/08/1931380634758627632_0.jpg,",
    "isReply": false,
    "isRetweet": false,
    "isSelfThread": false,
    "likes": 23,
    "replies": 4,
    "retweets": 0,
    "views": 9958,
    "originVideos": "https://video.twimg.com/amplify_video/1931358028122443776/vid/avc1/480x270/HhoPIAeFCq-ZvlFk.mp4"
  },
  {
    "id": "1931388180651221341",
    "accountId": "whyyoutouzhele",
    "sensitive": false,
    "name": "李老师不是你老师",
    "createdDate": "2025-06-08 00:30:00",
    "content": "近日，一名网友发帖吐槽，我要看看这个社会要烂到什么程度，引来众多网友回复。网友回复，玩不下去会掀桌子的。 https://t.co/tNPCncObmY",
    "images": "/tweet/image/whyyoutouzhele/2025/06/08/1931388180651221341_0.jpg,/tweet/image/whyyoutouzhele/2025/06/08/1931388180651221341_1.jpg,/tweet/image/whyyoutouzhele/2025/06/08/1931388180651221341_2.jpg,/tweet/image/whyyoutouzhele/2025/06/08/1931388180651221341_3.jpg,",
    "videos": "",
    "isReply": false,
    "isRetweet": false,
    "isSelfThread": false,
    "likes": 19,
    "replies": 5,
    "retweets": 1,
    "views": 8247,
    "originVideos": ""
  },
  {
    "id": "1931391955671335055",
    "accountId": "whyyoutouzhele",
    "sensitive": false,
    "name": "李老师不是你老师",
    "createdDate": "2025-06-08 00:45:00",
    "content": "据财新网近日报道，“五一”前夕，北京市第三中级法院有法官利用漏洞将几亿执行款转入私人账户并外逃。嫌疑人名叫白彬，2014年夏进入北京三中院执行局，案发前任执行助理法官。\n消息人士称，年初白彬向北京三中院提出辞职，至案发时尚未获准。白彬外逃早有准备，不仅钱款悉数转移国外，已获希腊国籍。事发系因其女友向闺蜜炫耀，隐私外泄，被人举报。白彬获知后，“五一”前全家出逃日本，目前下落不明。",
    "images": "/tweet/image/whyyoutouzhele/2025/06/08/1931391955671335055_0.jpg,/tweet/image/whyyoutouzhele/2025/06/08/1931391955671335055_1.jpg,",
    "videos": "",
    "isReply": false,
    "isRetweet": false,
    "isSelfThread": false,
    "likes": 52,
    "replies": 11,
    "retweets": 6,
    "views": 17944,
    "originVideos": ""
  },
  {
    "id": "1931399505057882541",
    "accountId": "whyyoutouzhele",
    "sensitive": false,
    "name": "李老师不是你老师",
    "createdDate": "2025-06-08 01:15:00",
    "content": "“求求你们把工资给了农民工吧”。6月6日，山西，沈阳永盛建设施工有限公司，阳城县分公司，欠薪。工人们在项目部讨薪。 https://t.co/Z2jPWnCse6",
    "images": "",
    "videos": "/tweet/video/whyyoutouzhele/2025/06/08/1931399505057882541_0.jpg,/tweet/video/whyyoutouzhele/2025/06/08/1931399505057882541_1.jpg,",
    "isReply": false,
    "isRetweet": false,
    "isSelfThread": false,
    "likes": 7,
    "replies": 0,
    "retweets": 2,
    "views": 1906,
    "originVideos": "https://video.twimg.com/amplify_video/1931366123963899905/vid/avc1/320x568/LWx8UI5Etu6rUgRt.mp4,https://video.twimg.com/amplify_video/1931366123980689409/vid/avc1/320x568/MS_k8I2QQCPlF0r6.mp4"
  },
  {
    "id": "1931395735179673793",
    "accountId": "whyyoutouzhele",
    "sensitive": false,
    "name": "李老师不是你老师",
    "createdDate": "2025-06-08 01:00:01",
    "content": "6月7日，中山比亚迪宿舍楼起火。 https://t.co/UI8fOYuDM3",
    "images": "/tweet/image/whyyoutouzhele/2025/06/08/1931395735179673793_0.jpg,",
    "videos": "/tweet/video/whyyoutouzhele/2025/06/08/1931395735179673793_0.jpg,",
    "isReply": false,
    "isRetweet": false,
    "isSelfThread": false,
    "likes": 25,
    "replies": 5,
    "retweets": 0,
    "views": 19835,
    "originVideos": "https://video.twimg.com/amplify_video/1931365353747034112/vid/avc1/320x568/0EFQR2AAkDpGWSk7.mp4"
  },
  {
    "id": "1931403281110126794",
    "accountId": "whyyoutouzhele",
    "sensitive": false,
    "name": "李老师不是你老师",
    "createdDate": "2025-06-08 01:30:00",
    "content": "台湾民主实验室最近发布了关于台湾TikTok抖音使用者的最新研究。研究显示，TikTok 的沉浸式体验与精准演算法正悄然重塑台湾社会的政治想像。\n量化调查显示，抖音活跃使用者更依赖网红作为资讯来源，他们对台湾政府制度的支持度较低，且在两岸议题上，虽然多数人认为中国政府是紧张关系主因，活跃使用者更倾向将责任分摊给民进党与美国，且对「中国武力攻台，美国不会援助台湾」的疑美论表现出更高认同。此外，他们更愿意接受「统一后生活变化不大」的观点，并在两岸关系中优先考虑经济利益更大于国家安全。\n同时，调查还发现，TikTok加剧了网路霸凌、擦边色情、诈骗及弱势族群被娱乐化等问题。\n\nhttps://t.co/IH22Z8lLqW從社群娛樂到統戰敘事-tiktok-在台灣社會心理防線的角色與重塑-6beb1480b819",
    "images": "/tweet/image/whyyoutouzhele/2025/06/08/1931403281110126794_0.jpg,",
    "videos": "",
    "isReply": false,
    "isRetweet": false,
    "isSelfThread": false,
    "likes": 26,
    "replies": 9,
    "retweets": 0,
    "views": 8007,
    "originVideos": ""
  },
  {
    "id": "1931407055123861870",
    "accountId": "whyyoutouzhele",
    "sensitive": false,
    "name": "李老师不是你老师",
    "createdDate": "2025-06-08 01:45:00",
    "content": "6月1日，湖南省永州市红星盛业农牧科技有限公司周边农田被养猪场排出的污水污染。\n6月6日，贵州乌江，被污染后的江水呈咖啡色。 https://t.co/itlbJvGA66",
    "images": "",
    "videos": "/tweet/video/whyyoutouzhele/2025/06/08/1931407055123861870_0.jpg,/tweet/video/whyyoutouzhele/2025/06/08/1931407055123861870_1.jpg,/tweet/video/whyyoutouzhele/2025/06/08/1931407055123861870_2.jpg,",
    "isReply": false,
    "isRetweet": false,
    "isSelfThread": false,
    "likes": 16,
    "replies": 8,
    "retweets": 2,
    "views": 11684,
    "originVideos": "https://video.twimg.com/amplify_video/1931370156237729792/vid/avc1/320x568/ZAWU2yFsyvqYciXT.mp4,https://video.twimg.com/amplify_video/1931370156250238976/vid/avc1/320x568/l78KvLnAb95xp7J-.mp4,https://video.twimg.com/amplify_video/1931370178937274368/vid/avc1/320x568/gmPCUO_wtbNBqHN-.mp4"
  }
]