[{"id":1737975106000,"createdDate":"2025-01-27 10:51","name":"英国广播公司","title":"緬甸詐騙風波影響泰國旅遊業 中國遊客憂安全問題：「避免和說中文的人交流」","content":"在泰國曼谷，一名來自中國浙江省的遊客對法新社表示，「我認為那些受騙的人是因為防範意識較低，所以我們在這裡不願意與說中文的人過多交流。」","newsLink":"https://www.bbc.com/zhongwen/articles/cn4mlmj71z2o/trad","thumbnail":"","detailImage":"news/detail/bbc/2025/01/27/1737975106000.webp","sourceId":"bbc"},{"id":1737966262000,"createdDate":"2025-01-27 08:24","name":"英国广播公司","title":"「朝小野大」格局下，台灣《憲法訴訟法》修法為何引發爭議？","content":"在台灣爭議不休的《憲法訴訟法》修正案，1月25日生效。這場修法是完善司法體制，還是立法院濫用權力干涉司法？未來的憲法法庭能持續發揮其功能嗎？","newsLink":"https://www.bbc.com/zhongwen/articles/c0lz4x943r4o/trad","thumbnail":"","detailImage":"news/detail/bbc/2025/01/27/1737966262000.webp","sourceId":"bbc"},{"id":1737964656000,"createdDate":"2025-01-27 07:57","name":"英国广播公司","title":"十公里外的自由：金門如何成為中國「敏感電影」的觀影天堂","content":"今年一月，一群來自中國福建省的影迷包團到金門看中國導演婁燁《一部未完成的電影》。BBC中文訪談多名中國影迷，他們特地到金門看「敏感電影」的理由。","newsLink":"https://www.bbc.com/zhongwen/articles/c62784rqqg8o/trad","thumbnail":"","detailImage":"news/detail/bbc/2025/01/27/1737964656000.webp","sourceId":"bbc"},{"id":1737984677000,"createdDate":"2025-01-27 13:31","name":"英国广播公司","title":"奧斯威辛如何成為納粹大屠殺的中心","content":"距離蘇聯軍隊解放奧斯威辛已經80年，現在這一天被定為大屠殺紀念日。","newsLink":"https://www.bbc.com/zhongwen/articles/cm29z444pevo/trad","thumbnail":"","detailImage":"news/detail/bbc/2025/01/27/1737984677000.webp","sourceId":"bbc"}]