[{"id":1753949220000,"createdDate":"2025-07-31 08:07","name":"德国之声","title":"台灣擬資助以色列定居點醫療 國際組織批評","content":"加薩饑荒與人道危機蔓延之際，國際社會持續加大對以色列的施壓。在這樣的氛圍下，台灣官員造訪以色列定居點，並洽談投資當地的醫療設施，遭質疑違反國際法。台灣外交部表示，該合作還在「研議討論」階段，尚無具體承諾。","newsLink":"https://www.dw.com/zh/台灣擬資助以色列定居點醫療-國際組織批評/a-73477615?maca=chi-rss-chi-all-1127-rdf","thumbnail":"","detailImage":"news/detail/dw/2025/07/31/1753949220000.webp","sourceId":"dw"},{"id":1753939680000,"createdDate":"2025-07-31 05:28","name":"德国之声","title":"美對日韓關稅都下調為15％　台灣將獲同等待遇？","content":"週三，美國與韓國達成貿易協議，美國對韓國的稅率降至15％，韓國則將在美投資3500億美元。美國對亞洲各國稅率陸續出爐，對台灣最終稅率則遲遲未公布，但有消息人士稱美方將給台灣「最優惠關稅」，換取台灣對美投資。","newsLink":"https://www.dw.com/zh/美對日韓關稅都下調為15％　台灣將獲同等待遇？/a-73476985?maca=chi-rss-chi-all-1127-rdf","thumbnail":"","detailImage":"news/detail/dw/2025/07/31/1753939680000.webp","sourceId":"dw"}]