[{"id":"1856741562513854715","name":"李老师不是你老师","accountId":"whyyoutouzhele","sensitive":false,"createdDate":"2024-11-14 00:50:59","content":"11月13日，广东佛山。大墩村的“怂仔”经营红酒生意，此前他曾多次举报村领导未果。\n当天，城管以红酒标签模糊为由，将其经营的红酒查收。查收过程引发村民不满和抗议。 https://t.co/F5psiqybuE","images":"","videos":"/tweet/video/whyyoutouzhele/2024/11/14/1856741562513854715_0.jpg,"},{"id":"1856741286822199771","name":"李老师不是你老师","accountId":"whyyoutouzhele","sensitive":false,"createdDate":"2024-11-14 00:49:54","content":"11月12日，福建福州。大量居民将一辆城管执法车团团围住，拍打引擎盖要求车里的城管出来，现场有大批警察维稳。  \n目前具体原因不明。 https://t.co/0OJ7enGYwX","images":"","videos":"/tweet/video/whyyoutouzhele/2024/11/14/1856741286822199771_0.jpg,"},{"id":"1856730583013163120","name":"李老师不是你老师","accountId":"whyyoutouzhele","sensitive":false,"createdDate":"2024-11-14 00:07:22","content":"11月13日，黑龙江鸡西。网曝当地新能源出租车要增加一元燃油附加费，并且司机没有任何社会保险，司机租车价格高达130元-220元/天，目前还要下调起步价。不满的司机们将出租车停在政府大楼前抗议。 https://t.co/oHkZYLMQOo","images":"/tweet/image/whyyoutouzhele/2024/11/14/1856730583013163120_0.jpg,","videos":"/tweet/video/whyyoutouzhele/2024/11/14/1856730583013163120_0.jpg,/tweet/video/whyyoutouzhele/2024/11/14/1856730583013163120_1.jpg,/tweet/video/whyyoutouzhele/2024/11/14/1856730583013163120_2.jpg,"}]