[{"id":1771892072000,"createdDate":"2026-02-24 00:14","name":"英国广播公司","title":"記錄「新疆再教育營」的中國青年關恆在美被關押半年後獲釋：「失去自由之後，才更意識到它的重要性」","content":"在被美國移民和海關執法局（ICE）逮捕並拘留了接近半年的時間後，中國公民關恆的庇護申請終於獲得美國移民法官的批准。","newsLink":"https://www.bbc.com/zhongwen/articles/cd6zjll5w75o/trad?at_medium=RSS&at_campaign=rss","thumbnail":"","detailImage":"news/detail/bbc/2026/02/24/1771892072000.webp","sourceId":"bbc"},{"id":1771915927000,"createdDate":"2026-02-24 06:52","name":"英国广播公司","title":"墨西哥販毒集團騷亂會不會影響今夏世界盃？","content":"暴力最初從墨西哥中西部的哈利斯科州開始，當地已進入紅色警戒安全狀態，但現在已蔓延至至少十多個區域。","newsLink":"https://www.bbc.com/zhongwen/articles/c15xlkeljdwo/trad?at_medium=RSS&at_campaign=rss","thumbnail":"","detailImage":"news/detail/bbc/2026/02/24/1771915927000.webp","sourceId":"bbc"},{"id":1771913935000,"createdDate":"2026-02-24 06:18","name":"英国广播公司","title":"特朗普威脅已有貿易協定國家別「玩花樣」","content":"此前，最高法院於週五裁定，特朗普實施全球關稅計劃時超越了其權限。目前全球多國表示正在評估哪些關稅與貿易協議仍然有效。","newsLink":"https://www.bbc.com/zhongwen/articles/cze0rr402wwo/trad?at_medium=RSS&at_campaign=rss","thumbnail":"","detailImage":"news/detail/bbc/2026/02/24/1771913935000.webp","sourceId":"bbc"},{"id":1771913016000,"createdDate":"2026-02-24 06:03","name":"英国广播公司","title":"菲律賓前總統杜特爾特因「反人類罪」受審：你需要知道的事","content":"在杜特爾特那場漫長且血腥的禁毒戰爭中，已有數千人被殺，而現在他面臨指控。","newsLink":"https://www.bbc.com/zhongwen/articles/c9wnyd7pywpo/trad?at_medium=RSS&at_campaign=rss","thumbnail":"","detailImage":"news/detail/bbc/2026/02/24/1771913016000.webp","sourceId":"bbc"},{"id":1771906923000,"createdDate":"2026-02-24 04:22","name":"英国广播公司","title":"對華逆差超千億美元，默茨首次訪華能否反轉中德「零和」競爭？","content":"有分析預測，德國未來應該會將兩國關係定位為「戰略夥伴」與「系統性競爭者」並存的雙重框架。","newsLink":"https://www.bbc.com/zhongwen/articles/c5yvl7g1epdo/trad?at_medium=RSS&at_campaign=rss","thumbnail":"","detailImage":"news/detail/bbc/2026/02/24/1771906923000.webp","sourceId":"bbc"}]